[{"neighbors":[{"similarity":0.6868903875106689,"title":"History of the World: Part I","tmdb_id":10156},{"similarity":0.7202971201756507,"title":"Monty Python Live at the Hollywood Bowl","tmdb_id":11949},{"similarity":0.6650539800800251,"title":"Movie 43","tmdb_id":87818},{"similarity":0.6476722297072365,"title":"Dogma","tmdb_id":1832},{"similarity":0.6618757364050427,"title":"The Fisher King","tmdb_id":177},{"similarity":0.6424067682323189,"title":"A Fish Called Wanda","tmdb_id":623},{"similarity":0.5819058917648199,"title":"The Full Monty","tmdb_id":9427},{"similarity":0.578960125328834,"title":"The Ten","tmdb_id":13173},{"similarity":0.5753232157564718,"title":"The Gods Must Be Crazy","tmdb_id":8393},{"similarity":0.5743231728217065,"title":"Death at a Funeral","tmdb_id":2196},{"similarity":0.6268894670113806,"title":"The Man Who Killed Don Quixote","tmdb_id":297725},{"similarity":0.6249014351697757,"title":"The Hitchhiker's Guide to the Galaxy","tmdb_id":7453}],"tmdb_id":4543},{"neighbors":[{"similarity":0.8001575191905074,"title":"200 Cigarettes","tmdb_id":15256},{"similarity":0.7263374474231334,"title":"She's Funny That Way","tmdb_id":245906},{"similarity":0.7830768821680907,"title":"Something Wild","tmdb_id":11300},{"similarity":0.7195384690721437,"title":"The Lonely Guy","tmdb_id":27171},{"similarity":0.7044455709980477,"title":"Swingers","tmdb_id":10218},{"similarity":0.7669691988906291,"title":"Bright Lights, Big City","tmdb_id":17170},{"similarity":0.7013949322818862,"title":"About Last Night...","tmdb_id":18169},{"similarity":0.7415629327091627,"title":"New York Stories","tmdb_id":9686},{"similarity":0.7284743283026663,"title":"Shortbus","tmdb_id":1378},{"similarity":0.7230531138448677,"title":"The Last Days of Disco","tmdb_id":16980},{"similarity":0.7150137166564795,"title":"Nowhere","tmdb_id":1811},{"similarity":0.7001573483321578,"title":"Whatever Works","tmdb_id":19265}],"tmdb_id":10843},{"neighbors":[{"similarity":0.7775933511567578,"title":"Everyone Says I Love You","tmdb_id":9716},{"similarity":0.7438390446488039,"title":"The Daytrippers","tmdb_id":49806},{"similarity":0.7798080462388113,"title":"Hanging Up","tmdb_id":10385},{"similarity":0.7618590976993351,"title":"Home for the Holidays","tmdb_id":9089},{"similarity":0.7477347441337678,"title":"Husbands and Wives","tmdb_id":28384},{"similarity":0.7674751775302855,"title":"Margot at the Wedding","tmdb_id":13998},{"similarity":0.7446892789303402,"title":"The Meyerowitz Stories (New and Selected)","tmdb_id":396398},{"similarity":0.7232491706243999,"title":"Stuck in Love","tmdb_id":111969},{"similarity":0.6943472143472377,"title":"Whatever Works","tmdb_id":19265},{"similarity":0.7086369201794297,"title":"Prime","tmdb_id":2313},{"similarity":0.7061008301409257,"title":"You Hurt My Feelings","tmdb_id":890215},{"similarity":0.7400358193827953,"title":"This Is Where I Leave You","tmdb_id":239678}],"tmdb_id":5143},{"neighbors":[{"similarity":0.7310446425037661,"title":"Race","tmdb_id":323677},{"similarity":0.7121176612103887,"title":"The Boys in the Boat","tmdb_id":823452},{"similarity":0.6858866736637329,"title":"Eddie the Eagle","tmdb_id":319888},{"similarity":0.6566257552881446,"title":"Miracle","tmdb_id":14292},{"similarity":0.6663890311288712,"title":"Glory Road","tmdb_id":9918},{"similarity":0.6677026923076368,"title":"Pride","tmdb_id":234200},{"similarity":0.6419601583287075,"title":"Invictus","tmdb_id":22954},{"similarity":0.6693200370600794,"title":"Seabiscuit","tmdb_id":4464},{"similarity":0.6533839442679119,"title":"McFarland, USA","tmdb_id":228203},{"similarity":0.6262955991476074,"title":"Remember the Titans","tmdb_id":10637},{"similarity":0.6370221333924488,"title":"12 Mighty Orphans","tmdb_id":625169},{"similarity":0.6125189611604644,"title":"The Damned United","tmdb_id":21641}],"tmdb_id":9443},{"neighbors":[{"similarity":0.8101090807440767,"title":"Pretty in Pink","tmdb_id":11522},{"similarity":0.7963090228979837,"title":"Sixteen Candles","tmdb_id":15144},{"similarity":0.7635213590678408,"title":"Lucas","tmdb_id":13346},{"similarity":0.7576272623934776,"title":"Can't Buy Me Love","tmdb_id":12919},{"similarity":0.7882301476476506,"title":"Can't Hardly Wait","tmdb_id":15037},{"similarity":0.773126909864993,"title":"She's All That","tmdb_id":10314},{"similarity":0.7397664033130333,"title":"The Breakfast Club","tmdb_id":2108},{"similarity":0.7425953147398587,"title":"Cry-Baby","tmdb_id":9768},{"similarity":0.7464055092069312,"title":"Take Me Home Tonight","tmdb_id":50725},{"similarity":0.7438922264393444,"title":"Love Don't Co$t a Thing","tmdb_id":21542},{"similarity":0.7365374900628718,"title":"Never Been Kissed","tmdb_id":11355},{"similarity":0.7329909612976582,"title":"I Love You, Beth Cooper","tmdb_id":19840}],"tmdb_id":15143},{"neighbors":[{"similarity":0.7681486522635754,"title":"Piranha","tmdb_id":48374},{"similarity":0.7422686755806862,"title":"Deep Rising","tmdb_id":9457},{"similarity":0.7169038425245987,"title":"Crocodile","tmdb_id":40466},{"similarity":0.7306338495555141,"title":"Mega Shark vs. Giant Octopus","tmdb_id":17911},{"similarity":0.7074216105817548,"title":"Piranha II: The Spawning","tmdb_id":31646},{"similarity":0.7205191032233975,"title":"Leviathan","tmdb_id":14372},{"similarity":0.686630884855151,"title":"Piranha 3D","tmdb_id":43593},{"similarity":0.6861524554266291,"title":"Piranha 3DD","tmdb_id":71668},{"similarity":0.7168058151797436,"title":"The Beast Within","tmdb_id":40219},{"similarity":0.723940488493438,"title":"Without Warning","tmdb_id":44932},{"similarity":0.7295543277562923,"title":"Sea Fever","tmdb_id":507441},{"similarity":0.7179261090359531,"title":"Forbidden World","tmdb_id":42251}],"tmdb_id":29343},{"neighbors":[{"similarity":0.6262412835269096,"title":"Geronimo: An American Legend","tmdb_id":35588},{"similarity":0.6438543840562323,"title":"Revolution","tmdb_id":12701},{"similarity":0.6398444453195493,"title":"Braveheart","tmdb_id":197},{"similarity":0.6533957772663666,"title":"The Four Feathers","tmdb_id":9093},{"similarity":0.6579612761013379,"title":"Centurion","tmdb_id":23759},{"similarity":0.6569417841936955,"title":"Gladiator","tmdb_id":98},{"similarity":0.6426973826365542,"title":"13 Hours: The Secret Soldiers of Benghazi","tmdb_id":300671},{"similarity":0.6439752671347281,"title":"The Big Red One","tmdb_id":16121},{"similarity":0.6250171093211597,"title":"Michael Collins","tmdb_id":1770},{"similarity":0.625849510686933,"title":"Kingdom of Heaven","tmdb_id":1495},{"similarity":0.6346679088662107,"title":"Hart's War","tmdb_id":10592},{"similarity":0.6265206021269891,"title":"Flags of Our Fathers","tmdb_id":3683}],"tmdb_id":26843},{"neighbors":[{"similarity":0.7181740204526663,"title":"Weird Science","tmdb_id":11814},{"similarity":0.6411120591032795,"title":"Minutemen","tmdb_id":22371},{"similarity":0.6317050937634517,"title":"Like Father Like Son","tmdb_id":36914},{"similarity":0.6864282321534241,"title":"Revenge of the Nerds","tmdb_id":14052},{"similarity":0.6972205216060336,"title":"Real Genius","tmdb_id":14370},{"similarity":0.639050199279549,"title":"Three O'Clock High","tmdb_id":13339},{"similarity":0.6248020923862834,"title":"High School High","tmdb_id":9308},{"similarity":0.7002251912835502,"title":"My Science Project","tmdb_id":18252},{"similarity":0.6231893975307344,"title":"The New Guy","tmdb_id":10985},{"similarity":0.6324829581393114,"title":"Teen Wolf Too","tmdb_id":15582},{"similarity":0.6777540551336307,"title":"Dream a Little Dream","tmdb_id":15142},{"similarity":0.6572858096492002,"title":"Screwballs","tmdb_id":25164}],"tmdb_id":23943},{"neighbors":[{"similarity":0.6928161932560571,"title":"The Flight of Dragons","tmdb_id":27273},{"similarity":0.661804830673276,"title":"The Black Cauldron","tmdb_id":10957},{"similarity":0.6436311328699758,"title":"The Last Unicorn","tmdb_id":10150},{"similarity":0.6402858239243124,"title":"Willow","tmdb_id":847},{"similarity":0.6458794495862593,"title":"Quest for Camelot","tmdb_id":18937},{"similarity":0.6356601487970668,"title":"Unicorn Store","tmdb_id":423949},{"similarity":0.6440021553941795,"title":"MirrorMask","tmdb_id":14517},{"similarity":0.6637984204359564,"title":"Epic","tmdb_id":116711},{"similarity":0.6554210089563342,"title":"Wish","tmdb_id":1022796},{"similarity":0.6547688220106943,"title":"Dragon Rider","tmdb_id":523366},{"similarity":0.6540622628063836,"title":"Bogus","tmdb_id":3587},{"similarity":0.6519373000126375,"title":"The Pagemaster","tmdb_id":15139}],"tmdb_id":11243},{"neighbors":[{"similarity":0.779302767006818,"title":"Varsity Blues","tmdb_id":14709},{"similarity":0.739847903094315,"title":"Wildcats","tmdb_id":29355},{"similarity":0.7375835840901195,"title":"Necessary Roughness","tmdb_id":20704},{"similarity":0.7386765048435491,"title":"All the Right Moves","tmdb_id":18172},{"similarity":0.6904189482542887,"title":"Little Giants","tmdb_id":20726},{"similarity":0.7097137690682283,"title":"The Program","tmdb_id":18133},{"similarity":0.6717317656242082,"title":"The Best of Times","tmdb_id":30653},{"similarity":0.7319624201329443,"title":"The Comebacks","tmdb_id":10759},{"similarity":0.7300107575543197,"title":"The Replacements","tmdb_id":10393},{"similarity":0.7213941502864746,"title":"Not Another Teen Movie","tmdb_id":11397},{"similarity":0.6472877007643765,"title":"The Game Plan","tmdb_id":13680},{"similarity":0.7054128064555679,"title":"Everybody Wants Some!!","tmdb_id":295699}],"tmdb_id":20443},{"neighbors":[{"similarity":0.6692555612458855,"title":"Diary of a Wimpy Kid","tmdb_id":33217},{"similarity":0.6528174602807932,"title":"Camp Nowhere","tmdb_id":17745},{"similarity":0.6605479745000377,"title":"Good Boys","tmdb_id":521777},{"similarity":0.6760397058006116,"title":"The Last American Virgin","tmdb_id":27088},{"similarity":0.6797243703874576,"title":"Turbo Kid","tmdb_id":310135},{"similarity":0.6563640139458439,"title":"Meet Dave","tmdb_id":11260},{"similarity":0.6922180921937158,"title":"PG: Psycho Goreman","tmdb_id":670428},{"similarity":0.6487013212264159,"title":"The Adventures of Sharkboy and Lavagirl","tmdb_id":14199},{"similarity":0.6599908629574032,"title":"Honey, I Shrunk the Kids","tmdb_id":9354},{"similarity":0.653044764571428,"title":"One Crazy Summer","tmdb_id":18282},{"similarity":0.6574701324067145,"title":"The Wizard","tmdb_id":183},{"similarity":0.6480851171320522,"title":"The Outcasts","tmdb_id":306943}],"tmdb_id":14443},{"neighbors":[{"similarity":0.8494858246195656,"title":"Tomorrow Never Dies","tmdb_id":714},{"similarity":0.7990120657687865,"title":"GoldenEye","tmdb_id":710},{"similarity":0.7798495517840934,"title":"Die Another Day","tmdb_id":36669},{"similarity":0.7288005392179938,"title":"For Your Eyes Only","tmdb_id":699},{"similarity":0.7234362222929576,"title":"The Living Daylights","tmdb_id":708},{"similarity":0.7194909806093349,"title":"Licence to Kill","tmdb_id":709},{"similarity":0.7060335771188868,"title":"Quantum of Solace","tmdb_id":10764},{"similarity":0.6956119779460244,"title":"Casino Royale","tmdb_id":36557},{"similarity":0.6933951314320839,"title":"Skyfall","tmdb_id":37724},{"similarity":0.6842485638974609,"title":"A View to a Kill","tmdb_id":707},{"similarity":0.6715763442558261,"title":"No Time to Die","tmdb_id":370172},{"similarity":0.7014073326123968,"title":"Never Say Never Again","tmdb_id":36670}],"tmdb_id":36643},{"neighbors":[{"similarity":0.8968969228635947,"title":"Lethal Weapon 4","tmdb_id":944},{"similarity":0.8789660969115584,"title":"Lethal Weapon 2","tmdb_id":942},{"similarity":0.8128330577932575,"title":"Lethal Weapon","tmdb_id":941},{"similarity":0.7482877534640809,"title":"Beverly Hills Cop II","tmdb_id":96},{"similarity":0.7302527909642851,"title":"Rush Hour 3","tmdb_id":5174},{"similarity":0.7353022914065018,"title":"Another 48 Hrs.","tmdb_id":11595},{"similarity":0.7174012691551996,"title":"Bad Boys for Life","tmdb_id":38700},{"similarity":0.7155851334853639,"title":"Beverly Hills Cop III","tmdb_id":306},{"similarity":0.7132421570753928,"title":"Bad Boys: Ride or Die","tmdb_id":573435},{"similarity":0.6738611733057935,"title":"Rush Hour 2","tmdb_id":5175},{"similarity":0.6707124253496842,"title":"Bad Boys II","tmdb_id":8961},{"similarity":0.6611509316573422,"title":"F/X2","tmdb_id":16820}],"tmdb_id":943},{"neighbors":[{"similarity":0.762302566386676,"title":"Swimfan","tmdb_id":20616},{"similarity":0.7495670870543278,"title":"Shattered","tmdb_id":844398},{"similarity":0.7405481297707158,"title":"Secret Obsession","tmdb_id":612152},{"similarity":0.7393795226133231,"title":"The Boy Next Door","tmdb_id":241251},{"similarity":0.7720574245124366,"title":"The Stepfather","tmdb_id":25155},{"similarity":0.7329139264426614,"title":"Enough","tmdb_id":1957},{"similarity":0.7189735370419289,"title":"Unlawful Entry","tmdb_id":17494},{"similarity":0.7905818519529619,"title":"Never Talk to Strangers","tmdb_id":48781},{"similarity":0.7490734036925425,"title":"The Stepfather","tmdb_id":19904},{"similarity":0.7257367001119096,"title":"The Hand That Rocks the Cradle","tmdb_id":11087},{"similarity":0.7341670197662966,"title":"Raising Cain","tmdb_id":13937},{"similarity":0.7326427287932374,"title":"I Know Who Killed Me","tmdb_id":5857}],"tmdb_id":10543},{"neighbors":[{"similarity":0.7126129542033286,"title":"Happy Gilmore","tmdb_id":9614},{"similarity":0.6964835497003676,"title":"The Benchwarmers","tmdb_id":9957},{"similarity":0.6944320301183895,"title":"BASEketball","tmdb_id":14013},{"similarity":0.6888205378202072,"title":"Major League","tmdb_id":9942},{"similarity":0.6753125399259331,"title":"DodgeBall: A True Underdog Story","tmdb_id":9472},{"similarity":0.6749904840559959,"title":"Caddyshack","tmdb_id":11977},{"similarity":0.669186072495111,"title":"The Scout","tmdb_id":35233},{"similarity":0.6611779551155215,"title":"The Comebacks","tmdb_id":10759},{"similarity":0.7007452320682465,"title":"The Big Lebowski","tmdb_id":115},{"similarity":0.6987578533826052,"title":"Balls of Fury","tmdb_id":9750},{"similarity":0.6399445709259091,"title":"Bad News Bears","tmdb_id":13341},{"similarity":0.6374188396238473,"title":"Goon","tmdb_id":74387}],"tmdb_id":11543},{"neighbors":[{"similarity":0.7596476480414942,"title":"Brooklyn's Finest","tmdb_id":26390},{"similarity":0.749046854288779,"title":"Prince of the City","tmdb_id":32047},{"similarity":0.7198494042894635,"title":"Night Falls on Manhattan","tmdb_id":46027},{"similarity":0.7387511148552234,"title":"Q & A","tmdb_id":31598},{"similarity":0.7226363123364087,"title":"City Hall","tmdb_id":11062},{"similarity":0.7321636324293882,"title":"Fort Apache, the Bronx","tmdb_id":23668},{"similarity":0.7147565030107073,"title":"Training Day","tmdb_id":2034},{"similarity":0.7243347420462575,"title":"Bringing Out the Dead","tmdb_id":8649},{"similarity":0.7691870709878601,"title":"Bad Lieutenant: Port of Call New Orleans","tmdb_id":11699},{"similarity":0.7111215844638576,"title":"Pride and Glory","tmdb_id":13150},{"similarity":0.7031887444816812,"title":"Narc","tmdb_id":11022},{"similarity":0.7480767535921601,"title":"True Confessions","tmdb_id":32077}],"tmdb_id":12143},{"neighbors":[{"similarity":0.7442091480524136,"title":"The Book of Henry","tmdb_id":382614},{"similarity":0.7507072081107415,"title":"The Captive","tmdb_id":244761},{"similarity":0.6932130626246368,"title":"Before and After","tmdb_id":43566},{"similarity":0.6935767626780449,"title":"Domestic Disturbance","tmdb_id":11456},{"similarity":0.6907618592962779,"title":"My Son","tmdb_id":750253},{"similarity":0.7249143642848302,"title":"White Bird in a Blizzard","tmdb_id":157825},{"similarity":0.6860912580041851,"title":"Reservation Road","tmdb_id":8954},{"similarity":0.7084746297717022,"title":"Flightplan","tmdb_id":9315},{"similarity":0.7037412536259675,"title":"The Imposter","tmdb_id":84287},{"similarity":0.7009143499396493,"title":"Dark Places","tmdb_id":182560},{"similarity":0.7170613863382034,"title":"Gone","tmdb_id":79548},{"similarity":0.7235370069270363,"title":"The Forgotten","tmdb_id":10145}],"tmdb_id":30943},{"neighbors":[{"similarity":0.7183352878694342,"title":"Man of Tai Chi","tmdb_id":76544},{"similarity":0.7058334376023434,"title":"Aftermath","tmdb_id":390051},{"similarity":0.699310400407854,"title":"Redbelt","tmdb_id":12400},{"similarity":0.6883455213219787,"title":"Gladiator","tmdb_id":16219},{"similarity":0.683889530157772,"title":"The Quest","tmdb_id":9103},{"similarity":0.6835317373727102,"title":"Damage","tmdb_id":24832},{"similarity":0.6832512433493376,"title":"Born a Champion","tmdb_id":766931},{"similarity":0.6797447448010302,"title":"The King of the Kickboxers","tmdb_id":68895},{"similarity":0.6780842774941469,"title":"Silent Night","tmdb_id":891699},{"similarity":0.6689851772407782,"title":"Best of the Best 2","tmdb_id":32049},{"similarity":0.6628485067638455,"title":"Reign Over Me","tmdb_id":2355},{"similarity":0.6727118101924775,"title":"The Jacket","tmdb_id":9667}],"tmdb_id":10443},{"neighbors":[{"similarity":0.7626599729703961,"title":"The Exterminator","tmdb_id":37835},{"similarity":0.7232691924477022,"title":"New Jack City","tmdb_id":10952},{"similarity":0.7336728953294779,"title":"King of New York","tmdb_id":9558},{"similarity":0.7389460636976708,"title":"Kiss of Death","tmdb_id":6071},{"similarity":0.7245835844735776,"title":"Bullet","tmdb_id":14469},{"similarity":0.695045163024222,"title":"Brooklyn's Finest","tmdb_id":26390},{"similarity":0.7356025347671662,"title":"Dragged Across Concrete","tmdb_id":438674},{"similarity":0.6850874562872907,"title":"Deep Cover","tmdb_id":20676},{"similarity":0.6803045376092084,"title":"Boiling Point","tmdb_id":22213},{"similarity":0.7152818234375309,"title":"Colors","tmdb_id":10126},{"similarity":0.7144742329018344,"title":"Menace II Society","tmdb_id":9516},{"similarity":0.7011046746345679,"title":"Vigilante","tmdb_id":23587}],"tmdb_id":11443},{"neighbors":[{"similarity":0.7619528757990941,"title":"The Unborn","tmdb_id":13788},{"similarity":0.7615687211477559,"title":"Mara","tmdb_id":514277},{"similarity":0.781249797808154,"title":"The Boy","tmdb_id":321258},{"similarity":0.7574358393360399,"title":"The Turning","tmdb_id":492611},{"similarity":0.7531311793210819,"title":"Hereditary","tmdb_id":493922},{"similarity":0.746767952072114,"title":"Abandoned","tmdb_id":880841},{"similarity":0.748637614961183,"title":"The Cellar","tmdb_id":758724},{"similarity":0.7629744675313255,"title":"Grace","tmdb_id":21398},{"similarity":0.7387126409629436,"title":"The Watcher in the Woods","tmdb_id":21970},{"similarity":0.7338782896084441,"title":"Ghostland","tmdb_id":476299},{"similarity":0.7315661364022273,"title":"Don't Be Afraid of the Dark","tmdb_id":46261},{"similarity":0.7539578410173134,"title":"The Hand That Rocks the Cradle","tmdb_id":1362315}],"tmdb_id":32043},{"neighbors":[{"similarity":0.7038135845777183,"title":"Meantime","tmdb_id":57978},{"similarity":0.6865026408026721,"title":"All or Nothing","tmdb_id":12454},{"similarity":0.6769995675230038,"title":"Nil by Mouth","tmdb_id":21252},{"similarity":0.6435197719825945,"title":"Riff-Raff","tmdb_id":59058},{"similarity":0.6449816901915126,"title":"East Is East","tmdb_id":10557},{"similarity":0.6983185920159579,"title":"Margot at the Wedding","tmdb_id":13998},{"similarity":0.6704986672989026,"title":"Driving Lessons","tmdb_id":11404},{"similarity":0.6865171247980711,"title":"Another Year","tmdb_id":44009},{"similarity":0.7042370175745365,"title":"Tamara Drewe","tmdb_id":38961},{"similarity":0.670670449540203,"title":"Distant Voices, Still Lives","tmdb_id":41799},{"similarity":0.6773470861006649,"title":"Happy-Go-Lucky","tmdb_id":10503},{"similarity":0.6540116216983525,"title":"Submarine","tmdb_id":49020}],"tmdb_id":36843},{"neighbors":[{"similarity":0.7057790396760537,"title":"Ernest Goes to Camp","tmdb_id":18935},{"similarity":0.6615444363118932,"title":"Jury Duty","tmdb_id":19326},{"similarity":0.6285324955089618,"title":"Let's Go to Prison","tmdb_id":9809},{"similarity":0.5956619032180479,"title":"Stir Crazy","tmdb_id":21629},{"similarity":0.6902937973804125,"title":"Ernest Scared Stupid","tmdb_id":32685},{"similarity":0.5668007801787521,"title":"We're No Angels","tmdb_id":5971},{"similarity":0.6349801591182852,"title":"Ernest Saves Christmas","tmdb_id":26386},{"similarity":0.5860447281307493,"title":"Quick Change","tmdb_id":10729},{"similarity":0.5840854445340179,"title":"My Cousin Vinny","tmdb_id":10377},{"similarity":0.5488008317240988,"title":"Yellowbeard","tmdb_id":11609},{"similarity":0.5649822573013852,"title":"Bandits","tmdb_id":3172},{"similarity":0.5434013637266699,"title":"Life","tmdb_id":6522}],"tmdb_id":18943},{"neighbors":[{"similarity":0.8457375020721113,"title":"Herbie Fully Loaded","tmdb_id":11451},{"similarity":0.7570496413967559,"title":"Herbie Goes Bananas","tmdb_id":12129},{"similarity":0.6575655919623663,"title":"Cars 2","tmdb_id":49013},{"similarity":0.6668402746658042,"title":"Cars 3","tmdb_id":260514},{"similarity":0.6513564853900015,"title":"Cars","tmdb_id":920},{"similarity":0.6528285542423504,"title":"Bumblebee","tmdb_id":424783},{"similarity":0.6193824931799734,"title":"Vacation","tmdb_id":296099},{"similarity":0.6240476926440459,"title":"Speed Racer","tmdb_id":7459},{"similarity":0.6095889820913003,"title":"The Sandlot 2","tmdb_id":18500},{"similarity":0.604990656761429,"title":"Hotel Transylvania: Transformania","tmdb_id":585083},{"similarity":0.6144206691834038,"title":"The Cannonball Run","tmdb_id":11286},{"similarity":0.6257416659455413,"title":"Go!","tmdb_id":520765}],"tmdb_id":32643},{"neighbors":[{"similarity":0.8101451512136008,"title":"White Fang","tmdb_id":12227},{"similarity":0.7545588984269952,"title":"Balto","tmdb_id":21032},{"similarity":0.7453259225664649,"title":"Alaska","tmdb_id":36344},{"similarity":0.6792412639912605,"title":"Free Willy 2: The Adventure Home","tmdb_id":9073},{"similarity":0.7424954586507825,"title":"Homeward Bound: The Incredible Journey","tmdb_id":6878},{"similarity":0.688271514167787,"title":"Return to the Blue Lagoon","tmdb_id":13888},{"similarity":0.6755462552037971,"title":"Free Willy 3: The Rescue","tmdb_id":18519},{"similarity":0.736834412341561,"title":"Iron Will","tmdb_id":24767},{"similarity":0.7225131464533743,"title":"Brother Bear 2","tmdb_id":10010},{"similarity":0.7356436696042518,"title":"Never Cry Wolf","tmdb_id":14280},{"similarity":0.7222318541898917,"title":"Eight Below","tmdb_id":9036},{"similarity":0.7126206952441181,"title":"Homeward Bound II: Lost in San Francisco","tmdb_id":25059}],"tmdb_id":43643},{"neighbors":[{"similarity":0.732436465223993,"title":"Undisputed","tmdb_id":15070},{"similarity":0.7246282251394988,"title":"The Great White Hype","tmdb_id":20759},{"similarity":0.7320756513582187,"title":"Confidence","tmdb_id":10743},{"similarity":0.703616767742098,"title":"Play It to the Bone","tmdb_id":20761},{"similarity":0.7089930163804724,"title":"Fighting","tmdb_id":17336},{"similarity":0.6758989370591508,"title":"The Stunt Man","tmdb_id":42160},{"similarity":0.6975563726576437,"title":"The Grifters","tmdb_id":18129},{"similarity":0.7085762623641588,"title":"Heist","tmdb_id":11088},{"similarity":0.6826493802620618,"title":"Matchstick Men","tmdb_id":7270},{"similarity":0.6987687743440952,"title":"Dirty Rotten Scoundrels","tmdb_id":10141},{"similarity":0.7017081061509276,"title":"Snatch","tmdb_id":107},{"similarity":0.6883410080870485,"title":"Harlem Nights","tmdb_id":9085}],"tmdb_id":19143},{"neighbors":[{"similarity":0.766844131040086,"title":"Revenge of the Nerds II: Nerds in Paradise","tmdb_id":16889},{"similarity":0.8096574942151793,"title":"Revenge of the Nerds IV: Nerds in Love","tmdb_id":21029},{"similarity":0.7699293015119771,"title":"Revenge of the Nerds","tmdb_id":14052},{"similarity":0.6703007124053908,"title":"Porky's Revenge","tmdb_id":23919},{"similarity":0.644690440727298,"title":"Porky's II: The Next Day","tmdb_id":19698},{"similarity":0.6248890779612467,"title":"Ghoulies III: Ghoulies Go to College","tmdb_id":44909},{"similarity":0.6366675377366234,"title":"Grown Ups 2","tmdb_id":109418},{"similarity":0.5949193961010896,"title":"American Reunion","tmdb_id":71552},{"similarity":0.6595583105446676,"title":"Real Genius","tmdb_id":14370},{"similarity":0.6206850205440019,"title":"House Party 2","tmdb_id":16096},{"similarity":0.6184822955749474,"title":"Van Wilder 2: The Rise of Taj","tmdb_id":10032},{"similarity":0.6471940256597214,"title":"Teen Wolf Too","tmdb_id":15582}],"tmdb_id":18543},{"neighbors":[{"similarity":0.762029096614126,"title":"The Water Horse","tmdb_id":54318},{"similarity":0.7201143926850286,"title":"Scooby-Doo! and the Loch Ness Monster","tmdb_id":12902},{"similarity":0.647647030210682,"title":"The Legend of Ochi","tmdb_id":896536},{"similarity":0.6654808395507813,"title":"Harry and the Hendersons","tmdb_id":8989},{"similarity":0.6357878734601943,"title":"Bigfoot Family","tmdb_id":702525},{"similarity":0.6520518232521488,"title":"Missing Link","tmdb_id":458253},{"similarity":0.6286220166978769,"title":"Dinosaur","tmdb_id":10567},{"similarity":0.6467475660209652,"title":"Journey to the Center of the Earth","tmdb_id":88751},{"similarity":0.6361552119973117,"title":"Strange World","tmdb_id":877269},{"similarity":0.6343212363882028,"title":"The Sea Beast","tmdb_id":560057},{"similarity":0.619214844360507,"title":"Chupa","tmdb_id":736790},{"similarity":0.6190216338552581,"title":"The King's Daughter","tmdb_id":245842}],"tmdb_id":51043},{"neighbors":[{"similarity":0.6822573141535248,"title":"Rad","tmdb_id":13841},{"similarity":0.6516949904908163,"title":"Ice Princess","tmdb_id":13374},{"similarity":0.6413686888548437,"title":"Youngblood","tmdb_id":17465},{"similarity":0.6909040231315061,"title":"ATL","tmdb_id":13960},{"similarity":0.6093603040900368,"title":"Vision Quest","tmdb_id":30069},{"similarity":0.6032238706609155,"title":"Skater Girl","tmdb_id":785522},{"similarity":0.592819978467438,"title":"Whip It","tmdb_id":22798},{"similarity":0.5925680339237717,"title":"Stick It","tmdb_id":10115},{"similarity":0.6464142704922012,"title":"The Cutting Edge: Chasing the Dream","tmdb_id":15088},{"similarity":0.632281700839048,"title":"Johnny Tsunami","tmdb_id":24020},{"similarity":0.6561639486025099,"title":"Lords of Dogtown","tmdb_id":9787},{"similarity":0.6397209246732948,"title":"mid90s","tmdb_id":437586}],"tmdb_id":15043},{"neighbors":[{"similarity":0.7746628703139967,"title":"Michael","tmdb_id":2928},{"similarity":0.7068070659016044,"title":"Dogma","tmdb_id":1832},{"similarity":0.6664785448974154,"title":"Down to Earth","tmdb_id":16300},{"similarity":0.7123881656113603,"title":"Date with an Angel","tmdb_id":28370},{"similarity":0.6527084541069663,"title":"Bruce Almighty","tmdb_id":310},{"similarity":0.6517664815716304,"title":"Holy Man","tmdb_id":9713},{"similarity":0.7042514931957946,"title":"Angels in the Outfield","tmdb_id":24795},{"similarity":0.704907852558958,"title":"Good Fortune","tmdb_id":1114967},{"similarity":0.6285479256173738,"title":"Mr. Destiny","tmdb_id":2612},{"similarity":0.624810961790809,"title":"Defendor","tmdb_id":34769},{"similarity":0.682989479823704,"title":"The Heavenly Kid","tmdb_id":23614},{"similarity":0.6622034267049055,"title":"The Preacher's Wife","tmdb_id":21539}],"tmdb_id":25943},{"neighbors":[{"similarity":0.8095934032307651,"title":"Modigliani","tmdb_id":34308},{"similarity":0.6992580094148952,"title":"Caravaggio","tmdb_id":20537},{"similarity":0.7289426401139982,"title":"Frida","tmdb_id":1360},{"similarity":0.6900403319382793,"title":"Girl with a Pearl Earring","tmdb_id":3635},{"similarity":0.7352930422111194,"title":"Vicky Cristina Barcelona","tmdb_id":5038},{"similarity":0.6915888791782177,"title":"Colette","tmdb_id":454652},{"similarity":0.6981154275044699,"title":"Le Divorce","tmdb_id":9499},{"similarity":0.656111126232305,"title":"Mr. Turner","tmdb_id":245700},{"similarity":0.643876678997488,"title":"Tulip Fever","tmdb_id":257785},{"similarity":0.6843729347049051,"title":"Head in the Clouds","tmdb_id":18804},{"similarity":0.6878847788208372,"title":"Ch\u00e9ri","tmdb_id":22215},{"similarity":0.6780591797594409,"title":"Another 9 1/2 Weeks","tmdb_id":18167}],"tmdb_id":41843},{"neighbors":[{"similarity":0.7611641913303826,"title":"Wallace & Gromit: The Curse of the Were-Rabbit","tmdb_id":533},{"similarity":0.7550632480505696,"title":"Shaun the Sheep Movie","tmdb_id":263109},{"similarity":0.8199284577870535,"title":"Chicken Run: Dawn of the Nugget","tmdb_id":520758},{"similarity":0.7602412682462666,"title":"Fantastic Mr. Fox","tmdb_id":10315},{"similarity":0.7507956961000117,"title":"Babe","tmdb_id":9598},{"similarity":0.7530403182750623,"title":"Valiant","tmdb_id":14175},{"similarity":0.7692761445872622,"title":"Chicken Little","tmdb_id":9982},{"similarity":0.6874449720533055,"title":"Early Man","tmdb_id":387592},{"similarity":0.7245483533851119,"title":"Rock-A-Doodle","tmdb_id":20421},{"similarity":0.6908546551614134,"title":"Wallace & Gromit: Vengeance Most Fowl","tmdb_id":929204},{"similarity":0.7148097821717202,"title":"The Angry Birds Movie","tmdb_id":153518},{"similarity":0.7131641169745094,"title":"Free Birds","tmdb_id":175574}],"tmdb_id":7443},{"neighbors":[{"similarity":0.8124348123259859,"title":"How to Lose a Guy in 10 Days","tmdb_id":9919},{"similarity":0.8021512103844111,"title":"Down with Love","tmdb_id":10720},{"similarity":0.755000440451376,"title":"The Proposal","tmdb_id":18240},{"similarity":0.7547395190432483,"title":"Two Weeks Notice","tmdb_id":2642},{"similarity":0.7736499493374472,"title":"Runaway Bride","tmdb_id":4806},{"similarity":0.7308699743972522,"title":"Morning Glory","tmdb_id":38357},{"similarity":0.7829028700976517,"title":"Trainwreck","tmdb_id":271718},{"similarity":0.7302610865677267,"title":"Maid in Manhattan","tmdb_id":7303},{"similarity":0.7757113262956092,"title":"Picture Perfect","tmdb_id":9413},{"similarity":0.7798513685616943,"title":"What's Your Number?","tmdb_id":63492},{"similarity":0.7793572819382852,"title":"Someone Like You...","tmdb_id":12658},{"similarity":0.7745940596269502,"title":"Just Go with It","tmdb_id":50546}],"tmdb_id":20943},{"neighbors":[{"similarity":0.7068267374490116,"title":"Mean Creek","tmdb_id":12281},{"similarity":0.693403103313178,"title":"Ken Park","tmdb_id":7090},{"similarity":0.6931708898550084,"title":"Happiness","tmdb_id":10683},{"similarity":0.7559104888804726,"title":"Palo Alto","tmdb_id":192132},{"similarity":0.7307450123122005,"title":"The Man in the Moon","tmdb_id":17474},{"similarity":0.7265416215447044,"title":"The Lovely Bones","tmdb_id":7980},{"similarity":0.7307876787969929,"title":"Thirteen","tmdb_id":11023},{"similarity":0.7215034302168817,"title":"September","tmdb_id":22477},{"similarity":0.703115614123224,"title":"Snow Angels","tmdb_id":14054},{"similarity":0.6927301191722345,"title":"The Prince of Tides","tmdb_id":10333},{"similarity":0.709206144896,"title":"Lady Bird","tmdb_id":391713},{"similarity":0.7166191671734831,"title":"Poison Ivy","tmdb_id":9264}],"tmdb_id":1443},{"neighbors":[{"similarity":0.7352896125271007,"title":"The Crucifixion","tmdb_id":394830},{"similarity":0.7299729795377046,"title":"The Ritual","tmdb_id":1278950},{"similarity":0.7368525174329257,"title":"The Devil Inside","tmdb_id":76487},{"similarity":0.7233468615248941,"title":"The Rite","tmdb_id":48171},{"similarity":0.7190886481449222,"title":"Stigmata","tmdb_id":10307},{"similarity":0.7072974708165105,"title":"Deliver Us from Evil","tmdb_id":184346},{"similarity":0.7142688515869223,"title":"The Pope's Exorcist","tmdb_id":758323},{"similarity":0.7167599971196378,"title":"Incarnate","tmdb_id":241258},{"similarity":0.6922596923211105,"title":"The Last Exorcism","tmdb_id":38358},{"similarity":0.6920915300535481,"title":"The Vatican Tapes","tmdb_id":157544},{"similarity":0.6912457791798051,"title":"Prey for the Devil","tmdb_id":676547},{"similarity":0.6831008217334681,"title":"The Nun","tmdb_id":439079}],"tmdb_id":8643},{"neighbors":[{"similarity":0.7118414720727164,"title":"Singles","tmdb_id":11068},{"similarity":0.7644804590688206,"title":"Empire Records","tmdb_id":13531},{"similarity":0.7070143419278891,"title":"Someone Great","tmdb_id":515248},{"similarity":0.6976296128532028,"title":"Nick and Norah's Infinite Playlist","tmdb_id":12182},{"similarity":0.6622975192320991,"title":"Down to You","tmdb_id":10472},{"similarity":0.7130068975077436,"title":"Juliet, Naked","tmdb_id":458344},{"similarity":0.6676040304356226,"title":"Watching the Detectives","tmdb_id":22100},{"similarity":0.6641231189741449,"title":"The Last Kiss","tmdb_id":7511},{"similarity":0.7207089973219839,"title":"(500) Days of Summer","tmdb_id":19913},{"similarity":0.676817204852812,"title":"Forgetting Sarah Marshall","tmdb_id":9870},{"similarity":0.6946632290149628,"title":"The Break-Up","tmdb_id":9767},{"similarity":0.6915188100082211,"title":"Almost Famous","tmdb_id":786}],"tmdb_id":243},{"neighbors":[{"similarity":0.831183787683897,"title":"Kiss the Girls","tmdb_id":9437},{"similarity":0.7482711804408254,"title":"Alex Cross","tmdb_id":94348},{"similarity":0.6606791124828781,"title":"Ransom","tmdb_id":3595},{"similarity":0.6486400854148607,"title":"Proof of Life","tmdb_id":11983},{"similarity":0.6690704371617028,"title":"12 Rounds","tmdb_id":17134},{"similarity":0.7005409107858555,"title":"The Watcher","tmdb_id":10685},{"similarity":0.717942872771096,"title":"The Postcard Killings","tmdb_id":449756},{"similarity":0.67036126380996,"title":"Don't Say a Word","tmdb_id":12103},{"similarity":0.6637291871997465,"title":"Angel Has Fallen","tmdb_id":423204},{"similarity":0.6686031432483344,"title":"88 Minutes","tmdb_id":3489},{"similarity":0.6418546799339753,"title":"First Kill","tmdb_id":410554},{"similarity":0.6510854060978929,"title":"Taken 2","tmdb_id":82675}],"tmdb_id":2043},{"neighbors":[{"similarity":0.7881164304147172,"title":"In Dreams","tmdb_id":28902},{"similarity":0.7566136726071806,"title":"Raising Cain","tmdb_id":13937},{"similarity":0.7594562904365191,"title":"Anna","tmdb_id":227700},{"similarity":0.7747582840583911,"title":"Gothika","tmdb_id":4970},{"similarity":0.7268249697017974,"title":"Inland Empire","tmdb_id":1730},{"similarity":0.7292545839341773,"title":"Untraceable","tmdb_id":8090},{"similarity":0.7341846391537302,"title":"Strange Darling","tmdb_id":1029281},{"similarity":0.7623088946986003,"title":"Altered States","tmdb_id":11542},{"similarity":0.761744037790732,"title":"Brain Dead","tmdb_id":5898},{"similarity":0.7384775026848834,"title":"I Know Who Killed Me","tmdb_id":5857},{"similarity":0.7336631977549075,"title":"Maniac","tmdb_id":103620},{"similarity":0.7489324820345558,"title":"Malignant","tmdb_id":619778}],"tmdb_id":8843},{"neighbors":[{"similarity":0.811567416903383,"title":"The Finest Hours","tmdb_id":300673},{"similarity":0.7621894854205254,"title":"The Perfect Storm","tmdb_id":2133},{"similarity":0.7595427927369053,"title":"All Is Lost","tmdb_id":152747},{"similarity":0.7674232170769806,"title":"Last Breath","tmdb_id":972533},{"similarity":0.7173145228206206,"title":"Deepwater Horizon","tmdb_id":296524},{"similarity":0.7775874012289103,"title":"Men of Honor","tmdb_id":11978},{"similarity":0.736561334221712,"title":"Adrift","tmdb_id":429300},{"similarity":0.7024084646977344,"title":"Captain Phillips","tmdb_id":109424},{"similarity":0.6998723705970845,"title":"Kursk","tmdb_id":401200},{"similarity":0.6939554703317818,"title":"Cast Away","tmdb_id":8358},{"similarity":0.7415510253281701,"title":"Poseidon","tmdb_id":503},{"similarity":0.6973562209395642,"title":"The Impossible","tmdb_id":80278}],"tmdb_id":4643},{"neighbors":[{"similarity":0.8387377265782325,"title":"Four Christmases","tmdb_id":12193},{"similarity":0.8102381351108188,"title":"The Holiday","tmdb_id":1581},{"similarity":0.7959116692497035,"title":"Surviving Christmas","tmdb_id":15566},{"similarity":0.7933166643258074,"title":"Last Christmas","tmdb_id":549053},{"similarity":0.8088471914259178,"title":"Love the Coopers","tmdb_id":333348},{"similarity":0.7599686584293942,"title":"Your Christmas or Mine?","tmdb_id":865559},{"similarity":0.7820008051120262,"title":"Our Little Secret","tmdb_id":1234811},{"similarity":0.7467921709805073,"title":"The Princess Switch","tmdb_id":556803},{"similarity":0.784051641055793,"title":"Falling for Christmas","tmdb_id":833097},{"similarity":0.770667477320057,"title":"Happiest Season","tmdb_id":520172},{"similarity":0.7295436465747646,"title":"Jingle Bell Heist","tmdb_id":1218762},{"similarity":0.7635295253395874,"title":"Christmas Inheritance","tmdb_id":449755}],"tmdb_id":9043},{"neighbors":[{"similarity":0.7292243919401014,"title":"Feast of Love","tmdb_id":14313},{"similarity":0.7035304525157184,"title":"Sleepless in Seattle","tmdb_id":858},{"similarity":0.7303384737464789,"title":"Hope Springs","tmdb_id":21544},{"similarity":0.7295706433418017,"title":"Bounce","tmdb_id":10862},{"similarity":0.7112097484226372,"title":"Valentine's Day","tmdb_id":32856},{"similarity":0.6931026259470064,"title":"Something from Tiffany's","tmdb_id":916053},{"similarity":0.7541496252234953,"title":"P.S. I Love You","tmdb_id":6023},{"similarity":0.6998981811419753,"title":"Sweet November","tmdb_id":1921},{"similarity":0.7276050750679384,"title":"Bed of Roses","tmdb_id":20927},{"similarity":0.7023439783169143,"title":"A Big Bold Beautiful Journey","tmdb_id":1241921},{"similarity":0.7308286750394234,"title":"Nights in Rodanthe","tmdb_id":14326},{"similarity":0.7300819757222969,"title":"A Little Bit of Heaven","tmdb_id":45156}],"tmdb_id":25643},{"neighbors":[{"similarity":0.730135515047228,"title":"The Butcher's Wife","tmdb_id":20096},{"similarity":0.6838587287046344,"title":"Only You","tmdb_id":9058},{"similarity":0.6685896661301219,"title":"L.A. Story","tmdb_id":2107},{"similarity":0.6641404319231793,"title":"Just Like Heaven","tmdb_id":9007},{"similarity":0.6457813753426921,"title":"Ghost","tmdb_id":251},{"similarity":0.6302499970700418,"title":"Prelude to a Kiss","tmdb_id":2613},{"similarity":0.6281100880581104,"title":"Chances Are","tmdb_id":3064},{"similarity":0.6564342653800957,"title":"Two of a Kind","tmdb_id":32644},{"similarity":0.6492987700777906,"title":"A Life Less Ordinary","tmdb_id":8067},{"similarity":0.6256418632610318,"title":"Over Her Dead Body","tmdb_id":13160},{"similarity":0.6644750566646119,"title":"Bounce","tmdb_id":10862},{"similarity":0.6615955938244938,"title":"TiMER","tmdb_id":39545}],"tmdb_id":16643},{"neighbors":[{"similarity":0.7166902361397802,"title":"Enola Holmes","tmdb_id":497582},{"similarity":0.7930306955993264,"title":"Get a Clue","tmdb_id":26189},{"similarity":0.6456030660944769,"title":"Lemony Snicket's A Series of Unfortunate Events","tmdb_id":11774},{"similarity":0.6476534166720399,"title":"Harriet the Spy","tmdb_id":38223},{"similarity":0.6835991030128024,"title":"Enola Holmes 2","tmdb_id":829280},{"similarity":0.6787997436167467,"title":"Crooked House","tmdb_id":419835},{"similarity":0.682923706937174,"title":"The Sleepover","tmdb_id":626393},{"similarity":0.6649563115508338,"title":"Brick","tmdb_id":9270},{"similarity":0.6792627364366842,"title":"A Simple Favor","tmdb_id":484247},{"similarity":0.6620095743233365,"title":"Kiss Kiss Bang Bang","tmdb_id":5236},{"similarity":0.6628431029854374,"title":"Catch That Kid","tmdb_id":20483},{"similarity":0.664250489730505,"title":"The Bling Ring","tmdb_id":96936}],"tmdb_id":14043},{"neighbors":[{"similarity":0.6881146288667471,"title":"Dr. Dolittle 2","tmdb_id":10808},{"similarity":0.6685798488696415,"title":"The Wild Thornberrys Movie","tmdb_id":14317},{"similarity":0.6596760282043759,"title":"Doctor Dolittle","tmdb_id":3050},{"similarity":0.6559557689111142,"title":"Dr. Dolittle: Tail to the Chief","tmdb_id":27996},{"similarity":0.5793637184053093,"title":"Jungle 2 Jungle","tmdb_id":9446},{"similarity":0.5967617431599344,"title":"Spirit Untamed","tmdb_id":637693},{"similarity":0.6164676538123787,"title":"Snow Dogs","tmdb_id":11888},{"similarity":0.6016651972950522,"title":"The Brave Little Toaster to the Rescue","tmdb_id":20378},{"similarity":0.6026765759004332,"title":"Homeward Bound: The Incredible Journey","tmdb_id":6878},{"similarity":0.5986482909483962,"title":"102 Dalmatians","tmdb_id":10481},{"similarity":0.5848435476345563,"title":"All Dogs Go to Heaven 2","tmdb_id":19042},{"similarity":0.5839941876243514,"title":"Chestnut: Hero of Central Park","tmdb_id":34672}],"tmdb_id":18843},{"neighbors":[{"similarity":0.7808923815515055,"title":"Heist","tmdb_id":11088},{"similarity":0.7777625446186675,"title":"After the Sunset","tmdb_id":10589},{"similarity":0.765302929154636,"title":"The Score","tmdb_id":11371},{"similarity":0.7571518513215795,"title":"Takers","tmdb_id":22907},{"similarity":0.7581985865448462,"title":"Crime 101","tmdb_id":1171145},{"similarity":0.7531735233375457,"title":"Triple 9","tmdb_id":146198},{"similarity":0.7420088452276049,"title":"The Art of the Steal","tmdb_id":209247},{"similarity":0.7535353029608721,"title":"No Sudden Move","tmdb_id":649409},{"similarity":0.751002431908923,"title":"2 Guns","tmdb_id":136400},{"similarity":0.750334793713933,"title":"The Rip","tmdb_id":1306368},{"similarity":0.7483095987227298,"title":"Inside Man","tmdb_id":388},{"similarity":0.8118795392496805,"title":"Focus","tmdb_id":256591}],"tmdb_id":10743},{"neighbors":[{"similarity":0.7610048082110037,"title":"Cheap Thrills","tmdb_id":175291},{"similarity":0.7374747600413872,"title":"War on Everyone","tmdb_id":333663},{"similarity":0.7223256029881532,"title":"The Guard","tmdb_id":67913},{"similarity":0.7464153762886101,"title":"Things to Do in Denver When You're Dead","tmdb_id":400},{"similarity":0.7204548768062105,"title":"Brothers","tmdb_id":616446},{"similarity":0.7551349557807017,"title":"Palmetto","tmdb_id":30949},{"similarity":0.7520715690824852,"title":"Last Looks","tmdb_id":557946},{"similarity":0.7433788707772537,"title":"Kiss Kiss Bang Bang","tmdb_id":5236},{"similarity":0.7347694856068204,"title":"The Ice Harvest","tmdb_id":9005},{"similarity":0.753914974418694,"title":"Confidence","tmdb_id":10743},{"similarity":0.7307297566210392,"title":"The Way of the Gun","tmdb_id":1619},{"similarity":0.7318277260911881,"title":"Kill Me Three Times","tmdb_id":237756}],"tmdb_id":9843},{"neighbors":[{"similarity":0.7288668991201241,"title":"Laggies","tmdb_id":244264},{"similarity":0.7127259180493813,"title":"SubUrbia","tmdb_id":28059},{"similarity":0.7382429508772461,"title":"Larry Crowne","tmdb_id":59861},{"similarity":0.735604136668143,"title":"The Pallbearer","tmdb_id":23570},{"similarity":0.7059309792817551,"title":"Outside Providence","tmdb_id":14578},{"similarity":0.7174915768373559,"title":"The Wackness","tmdb_id":13990},{"similarity":0.7241205172725281,"title":"Driving Lessons","tmdb_id":11404},{"similarity":0.7016689230359379,"title":"Stargirl","tmdb_id":382748},{"similarity":0.7158372428251785,"title":"Nothing in Common","tmdb_id":29968},{"similarity":0.705001312958357,"title":"Henry Fool","tmdb_id":37410},{"similarity":0.7048428131714352,"title":"LOL","tmdb_id":80271},{"similarity":0.7118306063238339,"title":"Mystic Pizza","tmdb_id":11191}],"tmdb_id":13243},{"neighbors":[{"similarity":0.881168851333796,"title":"Anaconda 3: Offspring","tmdb_id":14863},{"similarity":0.856409612259024,"title":"Anacondas: The Hunt for the Blood Orchid","tmdb_id":11237},{"similarity":0.7568036258983125,"title":"Anaconda","tmdb_id":9360},{"similarity":0.6942515015497607,"title":"Lake Placid 2","tmdb_id":17038},{"similarity":0.663228701944213,"title":"Deep Blue Sea 3","tmdb_id":703745},{"similarity":0.6503685256945655,"title":"Deep Blue Sea 2","tmdb_id":492336},{"similarity":0.7023635331233392,"title":"Megaboa","tmdb_id":920081},{"similarity":0.6390513855067876,"title":"Meg 2: The Trench","tmdb_id":615656},{"similarity":0.6344993412630352,"title":"Cruel Jaws","tmdb_id":84060},{"similarity":0.618751513500163,"title":"Tremors 3: Back to Perfection","tmdb_id":10829},{"similarity":0.66277744276038,"title":"Anaconda","tmdb_id":1234731},{"similarity":0.6723912504267572,"title":"Snakes on a Plane","tmdb_id":326}],"tmdb_id":19543},{"neighbors":[{"similarity":0.6797344140030785,"title":"Empire of Dreams: The Story of the Star Wars Trilogy","tmdb_id":76180},{"similarity":0.6313169879572259,"title":"Jim & Andy: The Great Beyond","tmdb_id":469019},{"similarity":0.5915259816260701,"title":"Bruce Lee, the Legend","tmdb_id":44645},{"similarity":0.6900946193280921,"title":"The Matrix","tmdb_id":603},{"similarity":0.5724896574710195,"title":"The Pixar Story","tmdb_id":15302},{"similarity":0.6727388292050435,"title":"The Animatrix","tmdb_id":55931},{"similarity":0.5733284636522712,"title":"Stanley Kubrick: A Life in Pictures","tmdb_id":30416},{"similarity":0.571693740855294,"title":"American Movie","tmdb_id":14242},{"similarity":0.5706012225255438,"title":"Helvetica","tmdb_id":13348},{"similarity":0.5680812866669085,"title":"Best Worst Movie","tmdb_id":40819},{"similarity":0.5641352849830494,"title":"Indie Game: The Movie","tmdb_id":80215},{"similarity":0.5983613214981167,"title":"Return to Jurassic Park","tmdb_id":503210}],"tmdb_id":14543},{"neighbors":[{"similarity":0.7729355780838855,"title":"Paradise Hills","tmdb_id":487083},{"similarity":0.7367768948229093,"title":"Eden","tmdb_id":1042834},{"similarity":0.742725774604908,"title":"Mean Creek","tmdb_id":12281},{"similarity":0.8041379189373303,"title":"Wilderness","tmdb_id":11494},{"similarity":0.6996995971549212,"title":"Shut In","tmdb_id":629015},{"similarity":0.6974964755555302,"title":"American Carnage","tmdb_id":982752},{"similarity":0.71221185630967,"title":"Brokedown Palace","tmdb_id":17707},{"similarity":0.699904993720718,"title":"After the Dark","tmdb_id":198287},{"similarity":0.7100060951116515,"title":"Starred Up","tmdb_id":209276},{"similarity":0.69566903414584,"title":"The Experiment","tmdb_id":43549},{"similarity":0.6846938129919438,"title":"Super Dark Times","tmdb_id":396940},{"similarity":0.7046101914912114,"title":"The Kings of Summer","tmdb_id":156700}],"tmdb_id":14643},{"neighbors":[{"similarity":0.7755918608446339,"title":"Consecration","tmdb_id":884184},{"similarity":0.765333540142932,"title":"A Dark Song","tmdb_id":409297},{"similarity":0.731472571324978,"title":"The Well","tmdb_id":1091267},{"similarity":0.7259267935104436,"title":"Apostle","tmdb_id":424121},{"similarity":0.7191820259063781,"title":"From Within","tmdb_id":16167},{"similarity":0.7744426442563186,"title":"Blackwater Lane","tmdb_id":1215918},{"similarity":0.7259122823816099,"title":"Amulet","tmdb_id":653615},{"similarity":0.7574591062203999,"title":"Lord of Misrule","tmdb_id":853387},{"similarity":0.7566374436082383,"title":"Demonic","tmdb_id":234212},{"similarity":0.7547378313818159,"title":"The Dark","tmdb_id":17},{"similarity":0.7505417015458439,"title":"The Watcher in the Woods","tmdb_id":21970},{"similarity":0.7606613556532311,"title":"Darkness","tmdb_id":11056}],"tmdb_id":10943},{"neighbors":[{"similarity":0.7623189557235942,"title":"Mystic Pizza","tmdb_id":11191},{"similarity":0.6819021215906802,"title":"Better Than Chocolate","tmdb_id":18212},{"similarity":0.6739422540301103,"title":"Waitress","tmdb_id":10758},{"similarity":0.7326810626898838,"title":"Feast of Love","tmdb_id":14313},{"similarity":0.6683014393335921,"title":"Frankie and Johnny","tmdb_id":3784},{"similarity":0.6666633951980181,"title":"I Hate Valentine's Day","tmdb_id":20825},{"similarity":0.662107806240892,"title":"Little Italy","tmdb_id":523773},{"similarity":0.6588820418707363,"title":"The Ramen Girl","tmdb_id":18585},{"similarity":0.6573287970939992,"title":"No Reservations","tmdb_id":3638},{"similarity":0.6900831470680439,"title":"The Hottie & The Nottie","tmdb_id":63315},{"similarity":0.6861758763523861,"title":"Down to You","tmdb_id":10472},{"similarity":0.6722712441773222,"title":"Playing by Heart","tmdb_id":825}],"tmdb_id":14843},{"neighbors":[{"similarity":0.8366850492464708,"title":"Insidious","tmdb_id":49018},{"similarity":0.8197254090874638,"title":"The Haunting in Connecticut","tmdb_id":18781},{"similarity":0.8146592406028359,"title":"An American Haunting","tmdb_id":10008},{"similarity":0.7948366743276752,"title":"We Are Still Here","tmdb_id":291272},{"similarity":0.7851933135999385,"title":"The Amityville Horror","tmdb_id":10065},{"similarity":0.8284039016527266,"title":"The Conjuring 2","tmdb_id":259693},{"similarity":0.8195862369685842,"title":"The Conjuring: The Devil Made Me Do It","tmdb_id":423108},{"similarity":0.7805569483522723,"title":"Sinister","tmdb_id":82507},{"similarity":0.7868511068817665,"title":"Presence","tmdb_id":1140535},{"similarity":0.7576768323176377,"title":"The Darkness","tmdb_id":257345},{"similarity":0.7548492333300879,"title":"The Haunting in Connecticut 2: Ghosts of Georgia","tmdb_id":150202},{"similarity":0.7420223647959413,"title":"The Cellar","tmdb_id":758724}],"tmdb_id":138843},{"neighbors":[{"similarity":0.8152998892632894,"title":"The Hangover Part III","tmdb_id":109439},{"similarity":0.7325997204597929,"title":"The Hangover","tmdb_id":18785},{"similarity":0.6853923849838643,"title":"Horrible Bosses 2","tmdb_id":227159},{"similarity":0.6798792605731382,"title":"Vacation Friends 2","tmdb_id":869641},{"similarity":0.6789896927290746,"title":"The Inbetweeners 2","tmdb_id":242022},{"similarity":0.6640439567430837,"title":"Magic Mike XXL","tmdb_id":264999},{"similarity":0.6600997289503193,"title":"Ted 2","tmdb_id":214756},{"similarity":0.6464483275266366,"title":"Harold & Kumar Escape from Guantanamo Bay","tmdb_id":13335},{"similarity":0.653734512975708,"title":"Dumb and Dumber To","tmdb_id":100042},{"similarity":0.6441070266743985,"title":"Hot Tub Time Machine 2","tmdb_id":243938},{"similarity":0.6433921870085121,"title":"Grown Ups 2","tmdb_id":109418},{"similarity":0.6406895297345835,"title":"Meet the Fockers","tmdb_id":693}],"tmdb_id":45243},{"neighbors":[{"similarity":0.8066796414885726,"title":"Maze Runner: The Scorch Trials","tmdb_id":294254},{"similarity":0.7548113064510833,"title":"The Maze Runner","tmdb_id":198663},{"similarity":0.6760386222577205,"title":"The Hunger Games: Mockingjay - Part 2","tmdb_id":131634},{"similarity":0.6640864725518321,"title":"The Hunger Games: Mockingjay - Part 1","tmdb_id":131631},{"similarity":0.7180541467936306,"title":"Allegiant","tmdb_id":262504},{"similarity":0.6395898406250463,"title":"The Matrix Revolutions","tmdb_id":605},{"similarity":0.6266527602780373,"title":"The Hunger Games: Catching Fire","tmdb_id":101299},{"similarity":0.6898377097787061,"title":"Insurgent","tmdb_id":262500},{"similarity":0.6252997327896361,"title":"Harry Potter and the Deathly Hallows: Part 2","tmdb_id":12445},{"similarity":0.6330394315183888,"title":"Mortal Engines","tmdb_id":428078},{"similarity":0.6211682392606134,"title":"Jurassic World Dominion","tmdb_id":507086},{"similarity":0.6054633571028512,"title":"The Hobbit: The Battle of the Five Armies","tmdb_id":122917}],"tmdb_id":336843},{"neighbors":[{"similarity":0.6913977723271088,"title":"In the Name of the King: A Dungeon Siege Tale","tmdb_id":2312},{"similarity":0.7157228451382285,"title":"Assassin's Creed","tmdb_id":121856},{"similarity":0.6376034546978455,"title":"Warcraft","tmdb_id":68735},{"similarity":0.6502116950882422,"title":"Dragonslayer","tmdb_id":848},{"similarity":0.6816206536428017,"title":"Gods of Egypt","tmdb_id":205584},{"similarity":0.6481854625987337,"title":"Dungeons & Dragons","tmdb_id":11849},{"similarity":0.6457047884959882,"title":"Krull","tmdb_id":849},{"similarity":0.6771240135842922,"title":"The Scorpion King","tmdb_id":9334},{"similarity":0.6726841349980858,"title":"The Sword and the Sorcerer","tmdb_id":13945},{"similarity":0.6290927221784408,"title":"Eragon","tmdb_id":2486},{"similarity":0.6732362134680979,"title":"Lara Croft: Tomb Raider","tmdb_id":1995},{"similarity":0.6805900418825368,"title":"Uncharted","tmdb_id":335787}],"tmdb_id":9543},{"neighbors":[{"similarity":0.7675907051426606,"title":"Slumdog Millionaire","tmdb_id":12405},{"similarity":0.7449090819102184,"title":"Philomena","tmdb_id":205220},{"similarity":0.6941315571296465,"title":"Rabbit-Proof Fence","tmdb_id":9555},{"similarity":0.7085671974992146,"title":"The Good Lie","tmdb_id":250538},{"similarity":0.6953710370942011,"title":"Kundun","tmdb_id":9746},{"similarity":0.6603550280781678,"title":"The White Tiger","tmdb_id":628534},{"similarity":0.6641069155097271,"title":"Changeling","tmdb_id":3580},{"similarity":0.7179863317485681,"title":"Room","tmdb_id":264644},{"similarity":0.7044478804851126,"title":"The Namesake","tmdb_id":16727},{"similarity":0.6831291862562322,"title":"The Blind Side","tmdb_id":22881},{"similarity":0.6852628755413035,"title":"The Way Back","tmdb_id":49009},{"similarity":0.6918705137018126,"title":"The Glass Castle","tmdb_id":336000}],"tmdb_id":334543},{"neighbors":[{"similarity":0.8309289912151723,"title":"Hitman's Wife's Bodyguard","tmdb_id":522931},{"similarity":0.735260824778853,"title":"The Man from Toronto","tmdb_id":667739},{"similarity":0.7097928012057112,"title":"Killers","tmdb_id":37821},{"similarity":0.7103502719278331,"title":"The Killer's Game","tmdb_id":507241},{"similarity":0.6957334036042666,"title":"Mr. Right","tmdb_id":333385},{"similarity":0.7034123015266923,"title":"Fight or Flight","tmdb_id":1212855},{"similarity":0.6928521504217326,"title":"True Memoirs of an International Assassin","tmdb_id":339396},{"similarity":0.7444871313505931,"title":"Close","tmdb_id":460321},{"similarity":0.7062200741455038,"title":"Hitman: Agent 47","tmdb_id":249070},{"similarity":0.7110181881181559,"title":"Accident Man","tmdb_id":455236},{"similarity":0.7139146647555606,"title":"Old Guy","tmdb_id":1077782},{"similarity":0.7025436293707359,"title":"Triple Threat","tmdb_id":449985}],"tmdb_id":390043},{"neighbors":[{"similarity":0.794058235067649,"title":"The Possession of Hannah Grace","tmdb_id":434555},{"similarity":0.7808715746873205,"title":"Unrest","tmdb_id":10085},{"similarity":0.7329740216375548,"title":"The Void","tmdb_id":378018},{"similarity":0.7646960052055756,"title":"The Resurrected","tmdb_id":30694},{"similarity":0.784930849919571,"title":"Hereditary","tmdb_id":493922},{"similarity":0.7648760520087206,"title":"The Home","tmdb_id":926606},{"similarity":0.7523184608899112,"title":"It Follows","tmdb_id":270303},{"similarity":0.7627403528723706,"title":"Smile","tmdb_id":882598},{"similarity":0.746591365727719,"title":"Malignant","tmdb_id":619778},{"similarity":0.7590730428706745,"title":"I Am Not a Serial Killer","tmdb_id":381034},{"similarity":0.7529553793087187,"title":"Relic","tmdb_id":539181},{"similarity":0.7513008263665134,"title":"Censor","tmdb_id":663866}],"tmdb_id":397243},{"neighbors":[{"similarity":0.8360960198487146,"title":"War Machine","tmdb_id":1265609},{"similarity":0.8384073731427888,"title":"Independence Day","tmdb_id":602},{"similarity":0.791055165474813,"title":"Skyline","tmdb_id":42684},{"similarity":0.7894097451208004,"title":"Extinction","tmdb_id":429415},{"similarity":0.7909499343909527,"title":"Occupation: Rainfall","tmdb_id":688258},{"similarity":0.7785373239701113,"title":"Captive State","tmdb_id":429471},{"similarity":0.7877673300074832,"title":"Cosmic Sin","tmdb_id":681887},{"similarity":0.7512402602022452,"title":"The Tomorrow War","tmdb_id":588228},{"similarity":0.7805364486419595,"title":"Red Dawn","tmdb_id":60747},{"similarity":0.7628912255409539,"title":"Bushwick","tmdb_id":430354},{"similarity":0.8072088939859563,"title":"Battleship","tmdb_id":44833},{"similarity":0.7284506965115914,"title":"Edge of Tomorrow","tmdb_id":137113}],"tmdb_id":44943},{"neighbors":[{"similarity":0.7939617303203111,"title":"Marauders","tmdb_id":359412},{"similarity":0.8019883612665195,"title":"Triple 9","tmdb_id":146198},{"similarity":0.7873841435614732,"title":"The Trust","tmdb_id":301608},{"similarity":0.8129706062501072,"title":"The Rip","tmdb_id":1306368},{"similarity":0.8049715541189106,"title":"Crime 101","tmdb_id":1171145},{"similarity":0.764368079186935,"title":"Ambulance","tmdb_id":763285},{"similarity":0.7959524746241502,"title":"Takers","tmdb_id":22907},{"similarity":0.7780756867700142,"title":"Heat","tmdb_id":949},{"similarity":0.7789314050882733,"title":"Inside Man","tmdb_id":388},{"similarity":0.7942372506076393,"title":"Dragged Across Concrete","tmdb_id":438674},{"similarity":0.7380108031066352,"title":"Bandit","tmdb_id":842942},{"similarity":0.7705458006540509,"title":"No Good Deed","tmdb_id":2017}],"tmdb_id":449443},{"neighbors":[{"similarity":0.8323356072005135,"title":"Wake Up, Ron Burgundy: The Lost Movie","tmdb_id":9965},{"similarity":0.8472591552354083,"title":"Anchorman: The Legend of Ron Burgundy","tmdb_id":8699},{"similarity":0.6855387324284505,"title":"Horrible Bosses 2","tmdb_id":227159},{"similarity":0.6725272997890136,"title":"Super Troopers 2","tmdb_id":50022},{"similarity":0.6659209908926782,"title":"Grown Ups 2","tmdb_id":109418},{"similarity":0.6633013655668618,"title":"Entourage","tmdb_id":188222},{"similarity":0.700215232303485,"title":"Zoolander 2","tmdb_id":329833},{"similarity":0.6977356379598751,"title":"The Naked Gun","tmdb_id":1035259},{"similarity":0.6392897953789702,"title":"Dumb and Dumber To","tmdb_id":100042},{"similarity":0.6312288942375106,"title":"This Is 40","tmdb_id":89492},{"similarity":0.6263772169390607,"title":"Ted 2","tmdb_id":214756},{"similarity":0.6242682157570546,"title":"Meet the Fockers","tmdb_id":693}],"tmdb_id":109443},{"neighbors":[{"similarity":0.7157269600593517,"title":"Whiteout","tmdb_id":22787},{"similarity":0.7162773888514204,"title":"Hold the Dark","tmdb_id":395841},{"similarity":0.715342236178496,"title":"Night Hunter","tmdb_id":441282},{"similarity":0.6783969040810962,"title":"The Weight of Water","tmdb_id":13526},{"similarity":0.7061694493379074,"title":"Hangman","tmdb_id":323368},{"similarity":0.705849588405302,"title":"The Postcard Killings","tmdb_id":449756},{"similarity":0.6820915558418172,"title":"Damaged","tmdb_id":1105407},{"similarity":0.6714742494961625,"title":"D-Tox","tmdb_id":10375},{"similarity":0.6717811499446682,"title":"Insomnia","tmdb_id":320},{"similarity":0.6593476939148303,"title":"The Frozen Ground","tmdb_id":199373},{"similarity":0.6582317181217806,"title":"Affliction","tmdb_id":31662},{"similarity":0.6604576235404626,"title":"Mindcage","tmdb_id":1043565}],"tmdb_id":372343},{"neighbors":[{"similarity":0.7962793199318189,"title":"Jingle Jangle: A Christmas Journey","tmdb_id":622855},{"similarity":0.7269204755355053,"title":"Encanto","tmdb_id":568124},{"similarity":0.7485721708659107,"title":"Godmothered","tmdb_id":662546},{"similarity":0.7034101330249212,"title":"The Golden Compass","tmdb_id":2268},{"similarity":0.7523237688205007,"title":"Genie","tmdb_id":1189198},{"similarity":0.7345715795782788,"title":"A Boy Called Christmas","tmdb_id":615666},{"similarity":0.7425663967140325,"title":"Barbie in the Nutcracker","tmdb_id":15167},{"similarity":0.7283456949344204,"title":"Ella Enchanted","tmdb_id":14442},{"similarity":0.7333209150736502,"title":"Barbie and the Secret Door","tmdb_id":285733},{"similarity":0.7238265074471035,"title":"Noelle","tmdb_id":454467},{"similarity":0.6990496551195967,"title":"Inkheart","tmdb_id":2309},{"similarity":0.7064412872538577,"title":"Maleficent","tmdb_id":102651}],"tmdb_id":426543},{"neighbors":[{"similarity":0.827671708800315,"title":"Surrogates","tmdb_id":19959},{"similarity":0.8152799331369138,"title":"Runaway","tmdb_id":9507},{"similarity":0.8130873342136797,"title":"I, Robot","tmdb_id":2048},{"similarity":0.8146865198161792,"title":"Vice","tmdb_id":307663},{"similarity":0.7995243211336247,"title":"Zone 414","tmdb_id":675319},{"similarity":0.7833705818352976,"title":"Chappie","tmdb_id":198184},{"similarity":0.8099061385857853,"title":"Kill Command","tmdb_id":384798},{"similarity":0.7697847671587877,"title":"Impostor","tmdb_id":4965},{"similarity":0.7998483809167877,"title":"The Creator","tmdb_id":670292},{"similarity":0.7524861009902682,"title":"RoboCop","tmdb_id":97020},{"similarity":0.7923338168550179,"title":"Wifelike","tmdb_id":1001835},{"similarity":0.7847806875538973,"title":"The Machine","tmdb_id":174675}],"tmdb_id":262543},{"neighbors":[{"similarity":0.7516982500511453,"title":"Greenland","tmdb_id":524047},{"similarity":0.7814581203318215,"title":"Noah","tmdb_id":86834},{"similarity":0.7446256534334126,"title":"Legion","tmdb_id":22894},{"similarity":0.7214676773891391,"title":"Knowing","tmdb_id":13811},{"similarity":0.6878820883805132,"title":"2012","tmdb_id":14161},{"similarity":0.7205751475321033,"title":"San Andreas","tmdb_id":254128},{"similarity":0.7183405334196973,"title":"Geostorm","tmdb_id":274855},{"similarity":0.8015601624902258,"title":"The Remaining","tmdb_id":280002},{"similarity":0.7367890489021639,"title":"How It Ends","tmdb_id":475210},{"similarity":0.6756130036131583,"title":"Deep Impact","tmdb_id":8656},{"similarity":0.6734175598979232,"title":"Into the Storm","tmdb_id":216282},{"similarity":0.6689005705486664,"title":"The Day After Tomorrow","tmdb_id":435}],"tmdb_id":218043},{"neighbors":[{"similarity":0.7905097457148905,"title":"Subservience","tmdb_id":1064028},{"similarity":0.7783639027053589,"title":"Companion","tmdb_id":1084199},{"similarity":0.772567346098077,"title":"I Am Mother","tmdb_id":505948},{"similarity":0.7645495328004687,"title":"Wifelike","tmdb_id":1001835},{"similarity":0.7635987555613514,"title":"The Artifice Girl","tmdb_id":983282},{"similarity":0.7566092666094861,"title":"Ex Machina","tmdb_id":264660},{"similarity":0.7423290245687979,"title":"Transcendence","tmdb_id":157353},{"similarity":0.7372765789227897,"title":"Upgrade","tmdb_id":500664},{"similarity":0.7308597864440601,"title":"Morgan","tmdb_id":377264},{"similarity":0.7558074388217558,"title":"Vice","tmdb_id":307663},{"similarity":0.7134591293306182,"title":"Archive","tmdb_id":606234},{"similarity":0.7464332596886479,"title":"Zone 414","tmdb_id":675319}],"tmdb_id":411143},{"neighbors":[{"similarity":0.774097179870014,"title":"Carol","tmdb_id":258480},{"similarity":0.7679071073645037,"title":"I Can't Think Straight","tmdb_id":31216},{"similarity":0.7181483291439796,"title":"Desert Hearts","tmdb_id":294},{"similarity":0.7694894473391274,"title":"Below Her Mouth","tmdb_id":370663},{"similarity":0.7119389418176099,"title":"The World to Come","tmdb_id":506281},{"similarity":0.7490188087386328,"title":"Yentl","tmdb_id":10269},{"similarity":0.7355064580940583,"title":"Call Me by Your Name","tmdb_id":398818},{"similarity":0.7384843420553399,"title":"Beginners","tmdb_id":55347},{"similarity":0.7301805629109007,"title":"Imagine Me & You","tmdb_id":1544},{"similarity":0.7357426934797593,"title":"Summerland","tmdb_id":523977},{"similarity":0.7329824805372172,"title":"Jenny's Wedding","tmdb_id":342474},{"similarity":0.7172226189756838,"title":"My First Summer","tmdb_id":741011}],"tmdb_id":419743},{"neighbors":[{"similarity":0.8178184290502037,"title":"Batman and Harley Quinn","tmdb_id":408648},{"similarity":0.8210361332475647,"title":"Suicide Squad: Hell to Pay","tmdb_id":487242},{"similarity":0.7922737638438858,"title":"Suicide Squad","tmdb_id":297761},{"similarity":0.7216582568881972,"title":"Batman: Under the Red Hood","tmdb_id":40662},{"similarity":0.7538318070650505,"title":"Batman: The Killing Joke","tmdb_id":382322},{"similarity":0.7187513313007994,"title":"Batman Beyond: Return of the Joker","tmdb_id":16234},{"similarity":0.7109993236949931,"title":"Birds of Prey (and the Fantabulous Emancipation of One Harley Quinn)","tmdb_id":495764},{"similarity":0.7046861858663331,"title":"Batman: Soul of the Dragon","tmdb_id":732450},{"similarity":0.7031162220749335,"title":"Batman vs. Robin","tmdb_id":321528},{"similarity":0.7321597264213643,"title":"Batman: Year One","tmdb_id":69735},{"similarity":0.7077445099999512,"title":"Batman vs Teenage Mutant Ninja Turtles","tmdb_id":581997},{"similarity":0.6963200090518126,"title":"Son of Batman","tmdb_id":251519}],"tmdb_id":242643},{"neighbors":[{"similarity":0.729478073840022,"title":"Fire in the Sky","tmdb_id":15613},{"similarity":0.7404969476531963,"title":"Super 8","tmdb_id":37686},{"similarity":0.6943558290212382,"title":"Dreamcatcher","tmdb_id":6171},{"similarity":0.7029163891132155,"title":"Extraterrestrial","tmdb_id":265016},{"similarity":0.7327522488522482,"title":"Contact","tmdb_id":686},{"similarity":0.7216896544032831,"title":"Nope","tmdb_id":762504},{"similarity":0.7183229576992278,"title":"The Arrival","tmdb_id":10547},{"similarity":0.706366706805769,"title":"No One Will Save You","tmdb_id":820609},{"similarity":0.6932251683923139,"title":"Signs","tmdb_id":2675},{"similarity":0.6699163436662315,"title":"Invaders from Mars","tmdb_id":31909},{"similarity":0.6916023221067943,"title":"Bugonia","tmdb_id":701387},{"similarity":0.7456985488265524,"title":"Monolith","tmdb_id":1024721}],"tmdb_id":565743},{"neighbors":[{"similarity":0.7300596070536598,"title":"Happy-Go-Lucky","tmdb_id":10503},{"similarity":0.6906066597967185,"title":"Hector and the Search for Happiness","tmdb_id":254375},{"similarity":0.6780168629117588,"title":"Danny Collins","tmdb_id":256924},{"similarity":0.7120879415444837,"title":"It's Kind of a Funny Story","tmdb_id":43923},{"similarity":0.7196888328388829,"title":"A Good Person","tmdb_id":800787},{"similarity":0.7162463443633146,"title":"Me Before You","tmdb_id":296096},{"similarity":0.7134681894824412,"title":"All of Us Strangers","tmdb_id":994108},{"similarity":0.7163521552674171,"title":"Powder Blue","tmdb_id":17740},{"similarity":0.7125091082591711,"title":"Collateral Beauty","tmdb_id":345920},{"similarity":0.7011690651657558,"title":"About Time","tmdb_id":122906},{"similarity":0.6998433972292357,"title":"Rye Lane","tmdb_id":1049638},{"similarity":0.6897028125780293,"title":"Demolition","tmdb_id":303991}],"tmdb_id":141043},{"neighbors":[{"similarity":0.7082199916239535,"title":"The Infiltrator","tmdb_id":325789},{"similarity":0.6642078750283149,"title":"Savages","tmdb_id":82525},{"similarity":0.6568122283005623,"title":"The Counselor","tmdb_id":109091},{"similarity":0.6365026869632806,"title":"Tequila Sunrise","tmdb_id":10396},{"similarity":0.6558600257737242,"title":"Original Sin","tmdb_id":2057},{"similarity":0.633035121981798,"title":"Traffic","tmdb_id":1900},{"similarity":0.6192512245694985,"title":"Arkansas","tmdb_id":560204},{"similarity":0.6400983716947346,"title":"Revenge","tmdb_id":14249},{"similarity":0.6485880313158159,"title":"Colombiana","tmdb_id":62835},{"similarity":0.6030044676860323,"title":"Sicario","tmdb_id":273481},{"similarity":0.6124910813382729,"title":"Trade","tmdb_id":4170},{"similarity":0.6112846517484315,"title":"Snitch","tmdb_id":134411}],"tmdb_id":255343},{"neighbors":[{"similarity":0.8473457253346736,"title":"Little Monsters","tmdb_id":503125},{"similarity":0.7877401273644793,"title":"Scouts Guide to the Zombie Apocalypse","tmdb_id":273477},{"similarity":0.7440604398406742,"title":"Freaks of Nature","tmdb_id":218784},{"similarity":0.7973327380623874,"title":"Unhuman","tmdb_id":839678},{"similarity":0.7117589674689943,"title":"Mayhem","tmdb_id":429733},{"similarity":0.7129683695272307,"title":"The Video Dead","tmdb_id":26677},{"similarity":0.7117024482391342,"title":"The Dead Don't Die","tmdb_id":535581},{"similarity":0.745958897659434,"title":"Zombieland","tmdb_id":19908},{"similarity":0.706800288223042,"title":"Undead","tmdb_id":8991},{"similarity":0.7013666728143491,"title":"Survival of the Dead","tmdb_id":29426},{"similarity":0.6995139417257791,"title":"Braindead","tmdb_id":763},{"similarity":0.7317377059420224,"title":"Anna and the Apocalypse","tmdb_id":461928}],"tmdb_id":241843},{"neighbors":[{"similarity":0.7767732968496547,"title":"Kingdom of Heaven","tmdb_id":1495},{"similarity":0.756093536886749,"title":"A Knight's Tale","tmdb_id":9476},{"similarity":0.7072940566210347,"title":"The Last Duel","tmdb_id":617653},{"similarity":0.707277469829361,"title":"Outlaw King","tmdb_id":454227},{"similarity":0.7140057695064663,"title":"Centurion","tmdb_id":23759},{"similarity":0.7093089045402563,"title":"Braveheart","tmdb_id":197},{"similarity":0.7667257676745377,"title":"King Arthur","tmdb_id":9477},{"similarity":0.7002429612467859,"title":"William Tell","tmdb_id":1195631},{"similarity":0.7576326368399877,"title":"Flesh + Blood","tmdb_id":12775},{"similarity":0.742299921769665,"title":"Robin Hood","tmdb_id":20662},{"similarity":0.7261284716798668,"title":"Season of the Witch","tmdb_id":23047},{"similarity":0.6879725007005827,"title":"Henry V","tmdb_id":10705}],"tmdb_id":38543},{"neighbors":[{"similarity":0.6008457761128451,"title":"Roald Dahl's Matilda the Musical","tmdb_id":668482},{"similarity":0.5935387824655609,"title":"A Little Princess","tmdb_id":19101},{"similarity":0.5768778286502478,"title":"Madeline","tmdb_id":35680},{"similarity":0.5734269302440942,"title":"Nanny McPhee","tmdb_id":11283},{"similarity":0.5927633266446374,"title":"The Wild Thornberrys Movie","tmdb_id":14317},{"similarity":0.609448540457575,"title":"One Crazy Summer","tmdb_id":18282},{"similarity":0.6188488563290367,"title":"Are You There God? It's Me, Margaret.","tmdb_id":555285},{"similarity":0.5925992806313477,"title":"Nim's Island","tmdb_id":10488},{"similarity":0.5778543964481535,"title":"Matilda","tmdb_id":10830},{"similarity":0.6082371663896898,"title":"Mermaids","tmdb_id":4587},{"similarity":0.5842152066362554,"title":"Next Gen","tmdb_id":523777},{"similarity":0.6037332943887512,"title":"Uptown Girls","tmdb_id":14926}],"tmdb_id":38843},{"neighbors":[{"similarity":0.7298999507669792,"title":"Fruitvale Station","tmdb_id":157354},{"similarity":0.7142357700372371,"title":"Detroit","tmdb_id":407448},{"similarity":0.6959808056696591,"title":"Till","tmdb_id":854239},{"similarity":0.6856814827927414,"title":"The Long Walk Home","tmdb_id":51763},{"similarity":0.7365331735037209,"title":"Blindspotting","tmdb_id":489930},{"similarity":0.6695786416136236,"title":"Mississippi Burning","tmdb_id":1632},{"similarity":0.678867671190115,"title":"Judas and the Black Messiah","tmdb_id":583406},{"similarity":0.6775775392229318,"title":"Ghosts of Mississippi","tmdb_id":31908},{"similarity":0.7303579961909646,"title":"The Hate U Give","tmdb_id":470044},{"similarity":0.6969953600506319,"title":"Just Mercy","tmdb_id":522212},{"similarity":0.6942293989606821,"title":"Skin","tmdb_id":542417},{"similarity":0.6597510306210383,"title":"BlacKkKlansman","tmdb_id":487558}],"tmdb_id":536743},{"neighbors":[{"similarity":0.6871265152625028,"title":"This Is Where I Leave You","tmdb_id":239678},{"similarity":0.6819365084461773,"title":"The Big Wedding","tmdb_id":87567},{"similarity":0.6798793547197521,"title":"Parental Guidance","tmdb_id":88042},{"similarity":0.6819413987274189,"title":"Made in Italy","tmdb_id":659991},{"similarity":0.6426309207700154,"title":"Sweet Sixteen","tmdb_id":1376},{"similarity":0.6738295041197132,"title":"A Long Way Down","tmdb_id":141043},{"similarity":0.6516577618237673,"title":"Life Is Sweet","tmdb_id":36843},{"similarity":0.6789972851436767,"title":"Keeping Mum","tmdb_id":9687},{"similarity":0.6589026529780876,"title":"The People We Hate at the Wedding","tmdb_id":802372},{"similarity":0.6568987572091239,"title":"Parenthood","tmdb_id":1552},{"similarity":0.673915967384516,"title":"Death at a Funeral","tmdb_id":2196},{"similarity":0.6587530103398203,"title":"The Angels' Share","tmdb_id":103747}],"tmdb_id":276843},{"neighbors":[{"similarity":0.7687938130159603,"title":"Blink","tmdb_id":26203},{"similarity":0.7009177575911026,"title":"See for Me","tmdb_id":825808},{"similarity":0.7196965334785491,"title":"Eye of the Beholder","tmdb_id":18681},{"similarity":0.7204387208112513,"title":"The Silent Hour","tmdb_id":1047373},{"similarity":0.7021213231863863,"title":"Spider","tmdb_id":9613},{"similarity":0.7161517284228672,"title":"All I See Is You","tmdb_id":345923},{"similarity":0.7695653996311427,"title":"Sightless","tmdb_id":733156},{"similarity":0.6893113233326877,"title":"10x10","tmdb_id":505177},{"similarity":0.701339737339606,"title":"Kimi","tmdb_id":800510},{"similarity":0.6886970192218937,"title":"The Woman in the Window","tmdb_id":520663},{"similarity":0.6969265125422253,"title":"Faces in the Crowd","tmdb_id":70577},{"similarity":0.6962971619536326,"title":"Hurry Up Tomorrow","tmdb_id":1093237}],"tmdb_id":417643},{"neighbors":[{"similarity":0.825817321871878,"title":"The Clique","tmdb_id":34482},{"similarity":0.8050969537865726,"title":"Sleepover","tmdb_id":9893},{"similarity":0.7930834937943578,"title":"Mean Girls 2","tmdb_id":51481},{"similarity":0.7837696010375401,"title":"Frenemies","tmdb_id":84105},{"similarity":0.7770352164351958,"title":"Confessions of a Teenage Drama Queen","tmdb_id":11132},{"similarity":0.7689356981516691,"title":"Sydney White","tmdb_id":10760},{"similarity":0.8097319083004826,"title":"Do Revenge","tmdb_id":762968},{"similarity":0.7955660478831346,"title":"Easy A","tmdb_id":37735},{"similarity":0.7997491656281349,"title":"F the Prom","tmdb_id":487702},{"similarity":0.7421995569018046,"title":"Bratz","tmdb_id":14123},{"similarity":0.7251930213286836,"title":"Wild Child","tmdb_id":13971},{"similarity":0.7921190770619103,"title":"Mean Girls","tmdb_id":10625}],"tmdb_id":306943},{"neighbors":[{"similarity":0.6700704170687106,"title":"Raining Stones","tmdb_id":62463},{"similarity":0.6520595193547205,"title":"I, Daniel Blake","tmdb_id":374473},{"similarity":0.6488358343358724,"title":"Nil by Mouth","tmdb_id":21252},{"similarity":0.6471933064890667,"title":"The Old Oak","tmdb_id":970348},{"similarity":0.645496649264103,"title":"My Name Is Joe","tmdb_id":8129},{"similarity":0.6668926035842105,"title":"Once Were Warriors","tmdb_id":527},{"similarity":0.690510451124216,"title":"The Drop","tmdb_id":154400},{"similarity":0.6704996854015863,"title":"Small Things Like These","tmdb_id":1102493},{"similarity":0.6641118730808763,"title":"Fish Tank","tmdb_id":24469},{"similarity":0.6937529561806804,"title":"Dead Man's Shoes","tmdb_id":12877},{"similarity":0.6594503916227477,"title":"Sweet Sixteen","tmdb_id":1376},{"similarity":0.6689961639492907,"title":"First Reformed","tmdb_id":458737}],"tmdb_id":76543},{"neighbors":[{"similarity":0.7018213564026157,"title":"Unhuman","tmdb_id":839678},{"similarity":0.7185478171473937,"title":"Detention","tmdb_id":68684},{"similarity":0.6651382023052903,"title":"The Package","tmdb_id":503619},{"similarity":0.6611590558228638,"title":"Truth or Dare","tmdb_id":101179},{"similarity":0.6933227214305687,"title":"Lesbian Vampire Killers","tmdb_id":18238},{"similarity":0.6873683917527039,"title":"Knights of Badassdom","tmdb_id":74461},{"similarity":0.6669275297266197,"title":"Severance","tmdb_id":5072},{"similarity":0.6420949994193648,"title":"Shrooms","tmdb_id":14456},{"similarity":0.6846052303783765,"title":"Spontaneous","tmdb_id":604578},{"similarity":0.674181372288903,"title":"Return to Horror High","tmdb_id":45878},{"similarity":0.6739290393325833,"title":"Porno","tmdb_id":576004},{"similarity":0.648702407148038,"title":"Glorious","tmdb_id":939914}],"tmdb_id":457943},{"neighbors":[{"similarity":0.7701114364718561,"title":"Honor Society","tmdb_id":929170},{"similarity":0.7308239644277141,"title":"Prom Pact","tmdb_id":932430},{"similarity":0.7124291742815776,"title":"Stargirl","tmdb_id":382748},{"similarity":0.709876746971694,"title":"Sierra Burgess Is a Loser","tmdb_id":462919},{"similarity":0.6965420617617489,"title":"The Half of It","tmdb_id":597219},{"similarity":0.7088142643423984,"title":"Crush","tmdb_id":860159},{"similarity":0.6691061762825644,"title":"It's a Boy Girl Thing","tmdb_id":37725},{"similarity":0.6797015308079476,"title":"The Kissing Booth","tmdb_id":454983},{"similarity":0.6763302003802273,"title":"The Perfect Date","tmdb_id":543540},{"similarity":0.6682231611656028,"title":"LOL","tmdb_id":80271},{"similarity":0.7125723472169181,"title":"Work It","tmdb_id":612706},{"similarity":0.6815893262641199,"title":"Sidelined: The QB and Me","tmdb_id":957119}],"tmdb_id":507143},{"neighbors":[{"similarity":0.845615066850258,"title":"Top Gun","tmdb_id":744},{"similarity":0.7437143790191036,"title":"Iron Eagle","tmdb_id":11037},{"similarity":0.7259155086625716,"title":"Hot Shots!","tmdb_id":9595},{"similarity":0.6472767026044419,"title":"Terminator 2: Judgment Day","tmdb_id":280},{"similarity":0.6968531976704081,"title":"Devotion","tmdb_id":653851},{"similarity":0.7206628027964846,"title":"Stealth","tmdb_id":10048},{"similarity":0.7072422806201653,"title":"Fire Birds","tmdb_id":6470},{"similarity":0.6967706321501234,"title":"Firefox","tmdb_id":10724},{"similarity":0.683082840550859,"title":"Mission: Impossible - Fallout","tmdb_id":353081},{"similarity":0.6655211598925165,"title":"Broken Arrow","tmdb_id":9208},{"similarity":0.6628220779061839,"title":"Flight of the Intruder","tmdb_id":18886},{"similarity":0.6626393503355337,"title":"Navy Seals","tmdb_id":427910}],"tmdb_id":361743},{"neighbors":[{"similarity":0.7812367830828523,"title":"The Sea Beast","tmdb_id":560057},{"similarity":0.7174253201119203,"title":"Surf's Up","tmdb_id":9408},{"similarity":0.7049043051403006,"title":"Shark Tale","tmdb_id":10555},{"similarity":0.6904494018237284,"title":"Finding Nemo","tmdb_id":12},{"similarity":0.6957849661938159,"title":"Moana","tmdb_id":277834},{"similarity":0.7199827756906774,"title":"Onward","tmdb_id":508439},{"similarity":0.6800753237911649,"title":"Atlantis: The Lost Empire","tmdb_id":10865},{"similarity":0.6564809558005815,"title":"Marcel the Shell with Shoes On","tmdb_id":869626},{"similarity":0.7080629041102496,"title":"Wonder Park","tmdb_id":400157},{"similarity":0.6823799921440625,"title":"Elio","tmdb_id":1022787},{"similarity":0.6728142473411278,"title":"Monsters, Inc.","tmdb_id":585},{"similarity":0.6566182375161784,"title":"The Little Mermaid","tmdb_id":10144}],"tmdb_id":508943},{"neighbors":[{"similarity":0.8251651085052047,"title":"House of Spoils","tmdb_id":1014661},{"similarity":0.7561853581547969,"title":"Bodies Bodies Bodies","tmdb_id":520023},{"similarity":0.7228801605926378,"title":"Send Help","tmdb_id":1198994},{"similarity":0.7158630646033949,"title":"The Hunt","tmdb_id":514847},{"similarity":0.772690783224954,"title":"Fresh","tmdb_id":787752},{"similarity":0.7303846842807679,"title":"Get Away","tmdb_id":1201753},{"similarity":0.6924795590771957,"title":"Severance","tmdb_id":5072},{"similarity":0.7447866779352146,"title":"Blood Diner","tmdb_id":62132},{"similarity":0.7602755593229027,"title":"Infinity Pool","tmdb_id":667216},{"similarity":0.8017786753025539,"title":"What You Wish For","tmdb_id":1126934},{"similarity":0.7469477564970329,"title":"The Invitation","tmdb_id":306947},{"similarity":0.7912195963119928,"title":"The Cook, the Thief, His Wife & Her Lover","tmdb_id":7452}],"tmdb_id":593643},{"neighbors":[{"similarity":0.8045400791771157,"title":"Infinity Pool","tmdb_id":667216},{"similarity":0.785876802362543,"title":"The Beach House","tmdb_id":632304},{"similarity":0.7326481777284,"title":"Leave the World Behind","tmdb_id":726209},{"similarity":0.7317925024513734,"title":"What Lies Below","tmdb_id":716703},{"similarity":0.7601819631006191,"title":"Fantasy Island","tmdb_id":539537},{"similarity":0.7077913775156688,"title":"The Rental","tmdb_id":587496},{"similarity":0.7168945472668488,"title":"Significant Other","tmdb_id":901385},{"similarity":0.7132003913418348,"title":"Vivarium","tmdb_id":458305},{"similarity":0.7100206550397311,"title":"I See You","tmdb_id":524251},{"similarity":0.7489724751047269,"title":"A Cure for Wellness","tmdb_id":340837},{"similarity":0.7367852317906148,"title":"You Should Have Left","tmdb_id":514593},{"similarity":0.7129445188574501,"title":"Speak No Evil","tmdb_id":1114513}],"tmdb_id":631843},{"neighbors":[{"similarity":0.904722835459015,"title":"Sonic the Hedgehog 2","tmdb_id":675353},{"similarity":0.8283879605440907,"title":"Sonic the Hedgehog","tmdb_id":454626},{"similarity":0.6934936255628631,"title":"The Nut Job 2: Nutty by Nature","tmdb_id":335777},{"similarity":0.6600721366056339,"title":"Sing 2","tmdb_id":438695},{"similarity":0.669253594095631,"title":"The Angry Birds Movie 2","tmdb_id":454640},{"similarity":0.6656790427187588,"title":"The Super Mario Galaxy Movie","tmdb_id":1226863},{"similarity":0.666612301549367,"title":"Trolls World Tour","tmdb_id":446893},{"similarity":0.6517286001102582,"title":"Space Jam: A New Legacy","tmdb_id":379686},{"similarity":0.6929937671105061,"title":"A Shaun the Sheep Movie: Farmageddon","tmdb_id":422803},{"similarity":0.6555755025519584,"title":"Minions: The Rise of Gru","tmdb_id":438148},{"similarity":0.6552144893064609,"title":"Despicable Me 4","tmdb_id":519182},{"similarity":0.6427746009460624,"title":"Zootopia 2","tmdb_id":1084242}],"tmdb_id":939243},{"neighbors":[{"similarity":0.8138680281374813,"title":"Extraction","tmdb_id":545609},{"similarity":0.7475645862986776,"title":"The Expendables","tmdb_id":27578},{"similarity":0.7401990283909005,"title":"Expend4bles","tmdb_id":299054},{"similarity":0.7284315555778432,"title":"Escape Plan: The Extractors","tmdb_id":480042},{"similarity":0.7211342937353943,"title":"Fortress: Sniper's Eye","tmdb_id":883502},{"similarity":0.7237753466331913,"title":"John Wick: Chapter 4","tmdb_id":603692},{"similarity":0.7170139561724358,"title":"Mechanic: Resurrection","tmdb_id":278924},{"similarity":0.7578517956638775,"title":"Gunner","tmdb_id":5492},{"similarity":0.7008410301306639,"title":"John Wick: Chapter 2","tmdb_id":324552},{"similarity":0.7497604870374769,"title":"Hounds of War","tmdb_id":949484},{"similarity":0.7185754267182033,"title":"The Equalizer 2","tmdb_id":345887},{"similarity":0.7485057148204721,"title":"Mile 22","tmdb_id":347375}],"tmdb_id":697843},{"neighbors":[{"similarity":0.7732432071872657,"title":"Blue Bayou","tmdb_id":644089},{"similarity":0.6896115437056288,"title":"Past Lives","tmdb_id":666277},{"similarity":0.7144574653434936,"title":"Here","tmdb_id":940139},{"similarity":0.7245320171603067,"title":"Waves","tmdb_id":533444},{"similarity":0.6796974623908156,"title":"The Farewell","tmdb_id":565310},{"similarity":0.7029390798870911,"title":"In America","tmdb_id":10511},{"similarity":0.6969582479286824,"title":"Okja","tmdb_id":387426},{"similarity":0.6653415005693872,"title":"Honey Boy","tmdb_id":512263},{"similarity":0.6873376103736043,"title":"Winter's Bone","tmdb_id":39013},{"similarity":0.6998728300720463,"title":"40 Acres","tmdb_id":1319951},{"similarity":0.6855023496271533,"title":"Hillbilly Elegy","tmdb_id":592984},{"similarity":0.6709875864410834,"title":"We Live in Time","tmdb_id":1100099}],"tmdb_id":615643},{"neighbors":[{"similarity":0.7695869232593258,"title":"A.I. Artificial Intelligence","tmdb_id":644},{"similarity":0.7614434679554469,"title":"Real Steel","tmdb_id":39254},{"similarity":0.7513946388690526,"title":"Finch","tmdb_id":522402},{"similarity":0.7696344359755677,"title":"I, Robot","tmdb_id":2048},{"similarity":0.7751012427361138,"title":"Chappie","tmdb_id":198184},{"similarity":0.7687202712727649,"title":"The Creator","tmdb_id":670292},{"similarity":0.7185999192775805,"title":"D.A.R.Y.L.","tmdb_id":16248},{"similarity":0.7747624193899475,"title":"Mortal Engines","tmdb_id":428078},{"similarity":0.7572170674459544,"title":"Turbo Kid","tmdb_id":310135},{"similarity":0.7108954207182295,"title":"After Yang","tmdb_id":585378},{"similarity":0.7515613904897231,"title":"Surrogates","tmdb_id":19959},{"similarity":0.737419100894669,"title":"Kin","tmdb_id":425505}],"tmdb_id":777443},{"neighbors":[{"similarity":0.7239686464378152,"title":"The Witcher: Sirens of the Deep","tmdb_id":1203329},{"similarity":0.6816411946011457,"title":"The Rats: A Witcher Tale","tmdb_id":1571470},{"similarity":0.6319409688092711,"title":"In the Lost Lands","tmdb_id":324544},{"similarity":0.6096298192558626,"title":"The Last Witch Hunter","tmdb_id":274854},{"similarity":0.61699175667446,"title":"Werewolf by Night","tmdb_id":894205},{"similarity":0.6092031271322246,"title":"Season of the Witch","tmdb_id":23047},{"similarity":0.6044268281506285,"title":"Spellbound","tmdb_id":592983},{"similarity":0.587587470932853,"title":"In the Name of the King: A Dungeon Siege Tale","tmdb_id":2312},{"similarity":0.5919645202164817,"title":"Red Sonja","tmdb_id":13494},{"similarity":0.59190832775097,"title":"The Black Cauldron","tmdb_id":10957},{"similarity":0.5881703150553195,"title":"Nimona","tmdb_id":961323},{"similarity":0.5704990133371044,"title":"Hellboy","tmdb_id":1487}],"tmdb_id":666243},{"neighbors":[{"similarity":0.7193589972038075,"title":"Passenger 57","tmdb_id":10538},{"similarity":0.7145496928741107,"title":"Non-Stop","tmdb_id":225574},{"similarity":0.7649193777704378,"title":"Unlocked","tmdb_id":291276},{"similarity":0.7399081320790067,"title":"Cleaner","tmdb_id":1125899},{"similarity":0.7591084317686261,"title":"Survivor","tmdb_id":334074},{"similarity":0.7250911740255978,"title":"White House Down","tmdb_id":117251},{"similarity":0.7428666154635852,"title":"Final Score","tmdb_id":421658},{"similarity":0.7192120045856059,"title":"The Peacemaker","tmdb_id":6623},{"similarity":0.7363511643211779,"title":"Kandahar","tmdb_id":717930},{"similarity":0.7130793099284881,"title":"Interceptor","tmdb_id":831946},{"similarity":0.7343554326822977,"title":"The Amateur","tmdb_id":1087891},{"similarity":0.7456882609639031,"title":"Bastille Day","tmdb_id":333669}],"tmdb_id":595743},{"neighbors":[{"similarity":0.781499035449116,"title":"Presence","tmdb_id":1140535},{"similarity":0.7740170917717368,"title":"Boogeyman","tmdb_id":8968},{"similarity":0.763373325551276,"title":"Lights Out","tmdb_id":345911},{"similarity":0.7737113722314191,"title":"The Disappointments Room","tmdb_id":293452},{"similarity":0.7486912074032152,"title":"The Boogeyman","tmdb_id":532408},{"similarity":0.7513348997609309,"title":"The Open House","tmdb_id":485774},{"similarity":0.7403379841968168,"title":"The Lodge","tmdb_id":474764},{"similarity":0.772701837726288,"title":"Darkness","tmdb_id":11056},{"similarity":0.7372200647863654,"title":"Cellar Door","tmdb_id":1361292},{"similarity":0.7728902551874848,"title":"The Wretched","tmdb_id":605804},{"similarity":0.7713239178089986,"title":"Never Let Go","tmdb_id":814889},{"similarity":0.7486320183254895,"title":"The Cellar","tmdb_id":758724}],"tmdb_id":994143},{"neighbors":[{"similarity":0.740450552256767,"title":"The Housemaid","tmdb_id":1368166},{"similarity":0.7156834116809329,"title":"Mothers' Instinct","tmdb_id":758679},{"similarity":0.7182379508163976,"title":"Eileen","tmdb_id":664341},{"similarity":0.6910166315528143,"title":"Greta","tmdb_id":471506},{"similarity":0.701377154076602,"title":"Dolores Claiborne","tmdb_id":11929},{"similarity":0.6862291728755114,"title":"Black Bear","tmdb_id":624788},{"similarity":0.7180506869134315,"title":"Luckiest Girl Alive","tmdb_id":799546},{"similarity":0.73454033329358,"title":"Echo Valley","tmdb_id":1097311},{"similarity":0.7223170794872895,"title":"Resurrection","tmdb_id":872497},{"similarity":0.7264927266201093,"title":"Dream House","tmdb_id":69668},{"similarity":0.7155679427208709,"title":"The Woman in the Window","tmdb_id":520663},{"similarity":0.7429125118086012,"title":"Die My Love","tmdb_id":1033148}],"tmdb_id":802443},{"neighbors":[{"similarity":0.7714264700206236,"title":"Long Story Short","tmdb_id":763532},{"similarity":0.783985195137195,"title":"A Big Bold Beautiful Journey","tmdb_id":1241921},{"similarity":0.7574385903796751,"title":"Safety Not Guaranteed","tmdb_id":84332},{"similarity":0.7544366191132943,"title":"When We First Met","tmdb_id":433310},{"similarity":0.7307160872692958,"title":"About Time","tmdb_id":122906},{"similarity":0.7367344074038265,"title":"Fingernails","tmdb_id":790459},{"similarity":0.7074026347779614,"title":"Time Is Up","tmdb_id":763148},{"similarity":0.699209887560808,"title":"Sliding Doors","tmdb_id":10215},{"similarity":0.7376269640564279,"title":"Isn't It Romantic","tmdb_id":449563},{"similarity":0.6804610483552169,"title":"Kate & Leopold","tmdb_id":11232},{"similarity":0.7291213981815012,"title":"Time Freak","tmdb_id":451925},{"similarity":0.7063960145879193,"title":"Which Brings Me to You","tmdb_id":975043}],"tmdb_id":843543},{"neighbors":[{"similarity":0.7460445222248652,"title":"One Day","tmdb_id":51828},{"similarity":0.7784422398816813,"title":"Two Night Stand","tmdb_id":286554},{"similarity":0.7342335243339894,"title":"Man Up","tmdb_id":332340},{"similarity":0.7325353942600905,"title":"Rye Lane","tmdb_id":1049638},{"similarity":0.7513394970577315,"title":"Long Story Short","tmdb_id":763532},{"similarity":0.7459083269436136,"title":"A Lot Like Love","tmdb_id":8976},{"similarity":0.7444226729074871,"title":"Just My Luck","tmdb_id":10025},{"similarity":0.7580853341298899,"title":"Love at First Sight","tmdb_id":353577},{"similarity":0.7756240536976441,"title":"Destination Wedding","tmdb_id":489929},{"similarity":0.7742656859540196,"title":"Down to You","tmdb_id":10472},{"similarity":0.7528450179511805,"title":"About Fate","tmdb_id":828613},{"similarity":0.7407912245901588,"title":"Valentine's Day","tmdb_id":32856}],"tmdb_id":975043},{"neighbors":[{"similarity":0.7904127682323814,"title":"The Burning","tmdb_id":24124},{"similarity":0.7777574194743283,"title":"Behind the Mask: The Rise of Leslie Vernon","tmdb_id":10961},{"similarity":0.7940974327006001,"title":"Return to Horror High","tmdb_id":45878},{"similarity":0.7694298591582402,"title":"Hell Fest","tmdb_id":429476},{"similarity":0.7566242751900036,"title":"Terror Firmer","tmdb_id":14005},{"similarity":0.7753373287619254,"title":"The Final Girls","tmdb_id":293970},{"similarity":0.7560591367857351,"title":"Popcorn","tmdb_id":39875},{"similarity":0.8061032099052242,"title":"Madman","tmdb_id":47957},{"similarity":0.7902168503301537,"title":"Sleepaway Camp","tmdb_id":13567},{"similarity":0.7855184235633909,"title":"April Fool's Day","tmdb_id":24913},{"similarity":0.7624883245211487,"title":"The Prowler","tmdb_id":44247},{"similarity":0.7761633100977453,"title":"Friday the 13th","tmdb_id":4488}],"tmdb_id":999243},{"neighbors":[{"similarity":0.7003930411963137,"title":"The Burning Plain","tmdb_id":12165},{"similarity":0.6914286400838981,"title":"Great Expectations","tmdb_id":9410},{"similarity":0.6879735132653205,"title":"If Beale Street Could Talk","tmdb_id":465914},{"similarity":0.6842126247700195,"title":"Mississippi Masala","tmdb_id":41791},{"similarity":0.6981863602100353,"title":"Far from Heaven","tmdb_id":10712},{"similarity":0.7156092753173076,"title":"The Last Letter from Your Lover","tmdb_id":638449},{"similarity":0.7011692303728853,"title":"Summerland","tmdb_id":523977},{"similarity":0.70919865952894,"title":"Two Moon Junction","tmdb_id":5241},{"similarity":0.7082719636077256,"title":"Evening","tmdb_id":6022},{"similarity":0.6862010503011404,"title":"Brokeback Mountain","tmdb_id":142},{"similarity":0.7259216643331269,"title":"Black Snake Moan","tmdb_id":7874},{"similarity":0.7109603433791909,"title":"Forever My Girl","tmdb_id":417261}],"tmdb_id":921643},{"neighbors":[{"similarity":0.7342912723269333,"title":"Resort to Love","tmdb_id":785539},{"similarity":0.6806324299590059,"title":"People We Meet on Vacation","tmdb_id":1034716},{"similarity":0.6793587199636726,"title":"The Perfect Find","tmdb_id":561717},{"similarity":0.6727782738564313,"title":"Find Me Falling","tmdb_id":1255350},{"similarity":0.6980830388008035,"title":"Falling Inn Love","tmdb_id":623195},{"similarity":0.658317120512095,"title":"Mother of the Bride","tmdb_id":1093231},{"similarity":0.6458643005418335,"title":"Happiness for Beginners","tmdb_id":881209},{"similarity":0.6397404664989549,"title":"The Other End of the Line","tmdb_id":17334},{"similarity":0.639578093431036,"title":"The Life List","tmdb_id":1254786},{"similarity":0.639090261184167,"title":"Suburban Girl","tmdb_id":13525},{"similarity":0.699101226642868,"title":"The Map That Leads to You","tmdb_id":1312946},{"similarity":0.6593661053793524,"title":"Always Be My Maybe","tmdb_id":513576}],"tmdb_id":806643},{"neighbors":[{"similarity":0.7800694842657534,"title":"Hunger","tmdb_id":173672},{"similarity":0.7655191426516031,"title":"Open Grave","tmdb_id":215830},{"similarity":0.7990503768401853,"title":"House of 9","tmdb_id":19166},{"similarity":0.7540244272457138,"title":"Reeker","tmdb_id":14457},{"similarity":0.7971157864071647,"title":"Escape Room","tmdb_id":522681},{"similarity":0.7938920044795598,"title":"Circle","tmdb_id":335866},{"similarity":0.7156713626667627,"title":"The Bunker Game","tmdb_id":794234},{"similarity":0.708066860476552,"title":"ATM","tmdb_id":89691},{"similarity":0.7669090052520091,"title":"The Hunt","tmdb_id":514847},{"similarity":0.7352553366238999,"title":"Old Man","tmdb_id":766220},{"similarity":0.732766721054238,"title":"Alone","tmdb_id":509635},{"similarity":0.7366324507216606,"title":"All Fun and Games","tmdb_id":926599}],"tmdb_id":739643}]